Workbook
Name CursePool1: 'Relic Cacul Temp'!$U:$U
Name CursePool2: 'Relic Cacul Temp'!$X:$X
Name CursePool3: 'Relic Cacul Temp'!$AA:$AA
Name EffectPool1: 'Relic Cacul Temp'!$L:$L
Name EffectPool2: 'Relic Cacul Temp'!$O:$O
Name EffectPool3: 'Relic Cacul Temp'!$R:$R
Name EmptyID: Variable!$H$2
Name LanguageList: 'UI Language'!$1:$1

Sheet UI
A1: =HLOOKUP($B$1,Tbl_Language[#All],MATCH("Language",Tbl_Language[English],0)+1,FALSE) -> 語言 | B1: 繁體中文
A2: =HLOOKUP($B$1,Tbl_Language[#All],MATCH("Relic",Tbl_Language[English],0)+1,FALSE) -> 遺物 | B2: 229-遼闊的幽靜情景 (綠) | D2: ID | E2: Sort ID(Override ID)
A3: =HLOOKUP($B$1,Tbl_Language[#All],MATCH("AttachEffect 1",Tbl_Language[English],0)+1,FALSE) -> 效果1 | B3: 7000202-耐力＋３ | D3: {=IF(B3<>"",_xlfn.CHOOSECOLS(_xlfn.TEXTSPLIT(B3,"-"),1),EmptyID)} -> 7000202 | E3: {=IF(D3<>EmptyID,VLOOKUP(VALUE(_xlfn.CHOOSECOLS(_xlfn.TEXTSPLIT(B3,"-"),1)),Tbl_Effect[],MATCH("overrideEffectId",Tbl_Effect[#Headers],0),FALSE),9999999999999)} -> 1000
A4: =HLOOKUP($B$1,Tbl_Language[#All],MATCH("AttachEffect 2",Tbl_Language[English],0)+1,FALSE) -> 效果2 | B4: 7342400-以弓攻擊時，恢復ＨＰ | D4: {=IF(B4<>"",_xlfn.CHOOSECOLS(_xlfn.TEXTSPLIT(B4,"-"),1),EmptyID)} -> 7342400 | E4: {=IF(D4<>EmptyID,VLOOKUP(VALUE(_xlfn.CHOOSECOLS(_xlfn.TEXTSPLIT(B4,"-"),1)),Tbl_Effect[],MATCH("overrideEffectId",Tbl_Effect[#Headers],0),FALSE),9999999999999)} -> 10
A5: =HLOOKUP($B$1,Tbl_Language[#All],MATCH("AttachEffect 3",Tbl_Language[English],0)+1,FALSE) -> 效果3 | B5: 7000802-縮短技藝的冷卻時間＋３ | D5: {=IF(B5<>"",_xlfn.CHOOSECOLS(_xlfn.TEXTSPLIT(B5,"-"),1),EmptyID)} -> 7000802 | E5: {=IF(D5<>EmptyID,VLOOKUP(VALUE(_xlfn.CHOOSECOLS(_xlfn.TEXTSPLIT(B5,"-"),1)),Tbl_Effect[],MATCH("overrideEffectId",Tbl_Effect[#Headers],0),FALSE),9999999999999)} -> 1000
A6: =HLOOKUP($B$1,Tbl_Language[#All],MATCH("CurseEffect 1",Tbl_Language[English],0)+1,FALSE) -> 負面1 | D6: {=IF(B6<>"",_xlfn.CHOOSECOLS(_xlfn.TEXTSPLIT(B6,"-"),1),EmptyID)} -> 4294967295 | E6: {=IF(D6<>EmptyID,VLOOKUP(VALUE(_xlfn.CHOOSECOLS(_xlfn.TEXTSPLIT(B6,"-"),1)),Tbl_Effect[],MATCH("overrideEffectId",Tbl_Effect[#Headers],0),FALSE),9999999999999)} -> 9999999999999
A7: =HLOOKUP($B$1,Tbl_Language[#All],MATCH("CurseEffect 2",Tbl_Language[English],0)+1,FALSE) -> 負面2 | D7: {=IF(B7<>"",_xlfn.CHOOSECOLS(_xlfn.TEXTSPLIT(B7,"-"),1),EmptyID)} -> 4294967295 | E7: {=IF(D7<>EmptyID,VLOOKUP(VALUE(_xlfn.CHOOSECOLS(_xlfn.TEXTSPLIT(B7,"-"),1)),Tbl_Effect[],MATCH("overrideEffectId",Tbl_Effect[#Headers],0),FALSE),9999999999999)} -> 9999999999999
A8: =HLOOKUP($B$1,Tbl_Language[#All],MATCH("CurseEffect 3",Tbl_Language[English],0)+1,FALSE) -> 負面3 | D8: {=IF(B8<>"",_xlfn.CHOOSECOLS(_xlfn.TEXTSPLIT(B8,"-"),1),EmptyID)} -> 4294967295 | E8: {=IF(D8<>EmptyID,VLOOKUP(VALUE(_xlfn.CHOOSECOLS(_xlfn.TEXTSPLIT(B8,"-"),1)),Tbl_Effect[],MATCH("overrideEffectId",Tbl_Effect[#Headers],0),FALSE),9999999999999)} -> 9999999999999
A11: =HLOOKUP($B$1,Tbl_Language[#All],MATCH("Final Result",Tbl_Language[English],0)+1,FALSE) -> 最終遺物結果 | B11: ID | C11: =HLOOKUP($B$1,Tbl_Language[#All],MATCH("Name And Description",Tbl_Language[English],0)+1,FALSE) -> 名稱/敘述
A12: =HLOOKUP($B$1,Tbl_Language[#All],MATCH("Relic",Tbl_Language[English],0)+1,FALSE) -> 遺物 | B12: {=IF(B2<>"",_xlfn.CHOOSECOLS(_xlfn.TEXTSPLIT(B2,"-"),1),"")} -> 229 | C12: =IF(B12<>"",VLOOKUP(B12+0,ItemText[],IFERROR(MATCH($B$1,ItemText[#Headers],0),2),FALSE),"") -> 遼闊的幽靜情景
A13: =HLOOKUP($B$1,Tbl_Language[#All],MATCH("AttachEffect 1",Tbl_Language[English],0)+1,FALSE) -> 效果1 | B13: {=_xlfn.SORTBY(D3:D5,E3:E5,1,D3:D5,1)} -> 7342400 | C13: =IF(B13<>EmptyID,VLOOKUP(VLOOKUP(B13+0,Tbl_Effect[],3,FALSE),EffectName[],IFERROR(MATCH($B$1,EffectName[#Headers],0),2),FALSE),"") -> 以弓攻擊時，恢復ＨＰ
A14: =HLOOKUP($B$1,Tbl_Language[#All],MATCH("AttachEffect 2",Tbl_Language[English],0)+1,FALSE) -> 效果2 | B14: 7000202 | C14: =IF(B14<>EmptyID,VLOOKUP(VLOOKUP(B14+0,Tbl_Effect[],3,FALSE),EffectName[],IFERROR(MATCH($B$1,EffectName[#Headers],0),2),FALSE),"") -> 耐力＋３
A15: =HLOOKUP($B$1,Tbl_Language[#All],MATCH("AttachEffect 3",Tbl_Language[English],0)+1,FALSE) -> 效果3 | B15: 7000802 | C15: =IF(B15<>EmptyID,VLOOKUP(VLOOKUP(B15+0,Tbl_Effect[],3,FALSE),EffectName[],IFERROR(MATCH($B$1,EffectName[#Headers],0),2),FALSE),"") -> 縮短技藝的冷卻時間＋３
A16: =HLOOKUP($B$1,Tbl_Language[#All],MATCH("CurseEffect 1",Tbl_Language[English],0)+1,FALSE) -> 負面1 | B16: {=_xlfn.SORTBY(D6:D8,E3:E5,1,D3:D5,1)} -> 4294967295 | C16: =IF(B16<>EmptyID,VLOOKUP(VLOOKUP(B16+0,Tbl_Effect[],3,FALSE),EffectName[],IFERROR(MATCH($B$1,EffectName[#Headers],0),2),FALSE),"")
A17: =HLOOKUP($B$1,Tbl_Language[#All],MATCH("CurseEffect 2",Tbl_Language[English],0)+1,FALSE) -> 負面2 | B17: 4294967295 | C17: =IF(B17<>EmptyID,VLOOKUP(VLOOKUP(B17+0,Tbl_Effect[],3,FALSE),EffectName[],IFERROR(MATCH($B$1,EffectName[#Headers],0),2),FALSE),"")
A18: =HLOOKUP($B$1,Tbl_Language[#All],MATCH("CurseEffect 3",Tbl_Language[English],0)+1,FALSE) -> 負面3 | B18: 4294967295 | C18: =IF(B18<>EmptyID,VLOOKUP(VLOOKUP(B18+0,Tbl_Effect[],3,FALSE),EffectName[],IFERROR(MATCH($B$1,EffectName[#Headers],0),2),FALSE),"")

Sheet UI Language
A1: English | B1: 繁體中文 | C1: 簡體中文
A2: Relic | B2: 遺物 | C2: 遗物
A3: AttachEffect 1 | B3: 效果1 | C3: 效果1
A4: AttachEffect 2 | B4: 效果2 | C4: 效果2
A5: AttachEffect 3 | B5: 效果3 | C5: 效果3
A6: CurseEffect 1 | B6: 負面1 | C6: 负面1
A7: CurseEffect 2 | B7: 負面2 | C7: 负面2
A8: CurseEffect 3 | B8: 負面3 | C8: 负面3
A9: Language | B9: 語言 | C9: 语言
A10: Final Result | B10: 最終遺物結果 | C10: 最终遗物结果
A11: Name And Description | B11: 名稱/敘述 | C11: 名称/叙述

Sheet Relic Cacul Temp
A1: Relic ID | B1: =VLOOKUP(UI!B2,$H2:$K2000,2,FALSE) -> 229 | H1: Relic | I1: Relic ID | J1: Relic Color | K1: Relic Name | L1: 效果池1 | M1: 效果池1 ID | N1: 效果池1 敘述 | O1: 效果池2 | P1: 效果池2 ID | Q1: 效果池2 敘述 | R1: 效果池3 | S1: 效果池3 ID | T1: 效果池3 敘述 | U1: 負面池1 | V1: 負面池1 ID | W1: 負面池1 敘述 | X1: 負面池2 | Y1: 負面池2 ID | Z1: 負面池2 敘述 | AA1: 負面池3 | AB1: 負面池3 ID | AC1: 負面池3 敘述 | AE1: AttachEffect 1 Temp | AF1: AttachEffect 2 Temp | AG1: AttachEffect 3 Temp | AH1: Curse1 Temp | AI1: Curse2 Temp | AJ1: Curse3 Temp
B2: 正面效果1 | C2: 正面效果2 | D2: 正面效果3 | E2: 負面效果1 | F2: 負面效果2 | G2: 負面效果3 | H2: =IF(VALUE(I2)<>0,I2&"-"&K2&" ("&J2&")","") -> 1-%null% (紅) | I2: {=_xlfn.EXPAND(Tbl_Equip[ID],2000,,0)} -> 1 | J2: =_xlfn.IFNA(IF(I2<>0,VLOOKUP(VLOOKUP(I2,Tbl_Equip[],2,FALSE),Tbl_Color[],IFERROR(MATCH(UI!$B$1,Tbl_Color[#Headers],0),2),FALSE),""),"Unset") -> 紅 | K2: =_xlfn.IFNA(IF(I2<>0,VLOOKUP(I2,ItemText[],IFERROR(MATCH(UI!$B$1,ItemText[#Headers],0),2),FALSE),""),"Unset") -> %null% | L2: =IF(VALUE(M2)=0,"",M2&"-"&N2) -> 7000000-生命力＋１ | M2: {=_xlfn.EXPAND(IF(B3=-1,0,_xlfn.ANCHORARRAY(AE2)),2000,,0)} -> 7000000 | N2: =IF(VALUE(M2)=0,"",VLOOKUP(VLOOKUP(M2,Tbl_Effect[],3,FALSE),EffectName[],IFERROR(MATCH(UI!$B$1,EffectName[#Headers],0),2),FALSE)) -> 生命力＋１ | O2: =IF(VALUE(P2)=0,"",P2&"-"&Q2) -> 7000000-生命力＋１ | P2: {=_xlfn.EXPAND(IF(C3=-1,0,_xlfn.ANCHORARRAY(AF2)),2000,,0)} -> 7000000 | Q2: =IF(VALUE(P2)=0,"",VLOOKUP(VLOOKUP(P2,Tbl_Effect[],3,FALSE),EffectName[],IFERROR(MATCH(UI!$B$1,EffectName[#Headers],0),2),FALSE)) -> 生命力＋１ | R2: =IF(VALUE(S2)=0,"",S2&"-"&T2) -> 7000000-生命力＋１ | S2: {=_xlfn.EXPAND(IF(D3=-1,0,_xlfn.ANCHORARRAY(AG2)),2000,,0)} -> 7000000 | T2: =IF(VALUE(S2)=0,"",VLOOKUP(VLOOKUP(S2,Tbl_Effect[],3,FALSE),EffectName[],IFERROR(MATCH(UI!$B$1,EffectName[#Headers],0),2),FALSE)) -> 生命力＋１ | U2: =IF(VALUE(V2)=0,"",V2&"-"&W2) | V2: {=_xlfn.EXPAND(IF(E3=-1,0,_xlfn.ANCHORARRAY(AH2)),2000,,0)} -> 0 | W2: =IF(V2<>0,VLOOKUP(VLOOKUP(V2,Tbl_Effect[],3,FALSE),EffectName[],IFERROR(MATCH(UI!$B$1,EffectName[#Headers],0),2),FALSE),"") | X2: =IF(VALUE(Y2)=0,"",Y2&"-"&Z2) | Y2: {=_xlfn.EXPAND(IF(F3=-1,0,_xlfn.ANCHORARRAY(AI2)),2000,,0)} -> 0 | Z2: =IF(Y2<>0,VLOOKUP(VLOOKUP(Y2,Tbl_Effect[],3,FALSE),EffectName[],IFERROR(MATCH(UI!$B$1,EffectName[#Headers],0),2),FALSE),"") | AA2: =IF(VALUE(AB2)=0,"",AB2&"-"&AC2) | AB2: {=_xlfn.EXPAND(IF(G3=-1,0,_xlfn.ANCHORARRAY(AJ2)),2000,,0)} -> 0 | AC2: =IF(AB2<>0,VLOOKUP(VLOOKUP(AB2,Tbl_Effect[],3,FALSE),EffectName[],IFERROR(MATCH(UI!$B$1,EffectName[#Headers],0),2),FALSE),"") | AE2: {=_xlfn._xlws.FILTER(Tbl_Pool[attachEffectId], Tbl_Pool[ID] = B3)} -> 7000000 | AF2: {=_xlfn.LET( _xlpm.CurrentPool, C3, _xlpm.Selected1, B4, _xlpm.Conflict1, IF(_xlpm.Selected1="", "###", _xlfn.XLOOKUP(_xlpm.Selected1, Tbl_Effect[欄1], Tbl_Effect[compatibilityId], "###")), _xlpm.PoolEffects, _xlfn._xlws.FILTER(Tbl_Pool[attachEffectId], Tbl_Pool[ID] = _xlpm.CurrentPool, "無符合效果"), IF(ISERROR(_xlpm.PoolEffects), "請先完成前置選擇", _xlfn._xlws.FILTER(_xlpm.PoolEffects, (_xlpm.PoolEffects <> _xlpm.Selected1) * ( (_xlpm.Conflict1 = -1) + (_xlfn.XLOOKUP(_xlpm.PoolEffects, Tbl_Effect[欄1], Tbl_Effect[compatibilityId], "") <> _xlpm.Conflict1) ) ) ) )} -> 7000000 | AG2: {=_xlfn.LET( _xlpm.CurrentPool, D3, _xlpm.Selected1, B4, _xlpm.Selected2, C4, _xlpm.Conflict1, IF(_xlpm.Selected1="", "###", _xlfn.XLOOKUP(_xlpm.Selected1, Tbl_Effect[欄1], Tbl_Effect[compatibilityId], "###")), _xlpm.Conflict2, IF(_xlpm.Selected2="", "###", _xlfn.XLOOKUP(_xlpm.Selected2, Tbl_Effect[欄1], Tbl_Effect[compatibilityId], "###")), _xlpm.PoolEffects, _xlfn._xlws.FILTER(Tbl_Pool[attachEffectId], Tbl_Pool[ID] = _xlpm.CurrentPool, "無符合效果"), IF(ISERROR(_xlpm.PoolEffects), "請先完成前置選擇", _xlfn._xlws.FILTER(_xlpm.PoolEffects, (_xlpm.PoolEffects <> _xlpm.Selected1) * (_xlpm.PoolEffects <> _xlpm.Selected2) * ((_xlpm.Conflict1 = -1) + (_xlfn.XLOOKUP(_xlpm.PoolEffects, Tbl_Effect[欄1], Tbl_Effect[compatibilityId], "") <> _xlpm.Conflict1)) * ((_xlpm.Conflict2 = -1) + (_xlfn.XLOOKUP(_xlpm.PoolEffects, Tbl_Effect[欄1], Tbl_Effect[compatibilityId], "") <> _xlpm.Conflict2)) ) ) )} -> 7000000 | AH2: {=IF(E3<>-1,_xlfn._xlws.FILTER(Tbl_Pool[attachEffectId], Tbl_Pool[ID] = E3),"無符合效果")} -> 無符合效果 | AI2: {=_xlfn.LET( _xlpm.CurrentPool, F3, _xlpm.CurseSelected1, E4, _xlpm.CurseConflict1, IF(_xlpm.CurseSelected1="", "###", _xlfn.XLOOKUP(_xlpm.CurseSelected1, Tbl_Effect[欄1], Tbl_Effect[compatibilityId], "###")), _xlpm.PoolEffects, _xlfn._xlws.FILTER(Tbl_Pool[attachEffectId], Tbl_Pool[ID] = _xlpm.CurrentPool, "無符合效果"), IF(ISERROR(_xlpm.PoolEffects), "請先完成前置選擇", _xlfn._xlws.FILTER(_xlpm.PoolEffects, (_xlpm.PoolEffects <> _xlpm.CurseSelected1) * ((_xlpm.CurseConflict1 = -1) + (_xlfn.XLOOKUP(_xlpm.PoolEffects, Tbl_Effect[欄1], Tbl_Effect[compatibilityId], "") <> _xlpm.CurseConflict1)) ) ) )} -> 無符合效果 | AJ2: {=_xlfn.LET( _xlpm.CurrentPool, G3, _xlpm.CurseSelected1, E4, _xlpm.CurseSelected2, F4, _xlpm.CurseConflict1, IF(_xlpm.CurseSelected1="", "###", _xlfn.XLOOKUP(_xlpm.CurseSelected1, Tbl_Effect[欄1], Tbl_Effect[compatibilityId], "###")), _xlpm.CurseConflict2, IF(_xlpm.CurseSelected2="", "###", _xlfn.XLOOKUP(_xlpm.CurseSelected2, Tbl_Effect[欄1], Tbl_Effect[compatibilityId], "###")), _xlpm.PoolEffects, _xlfn._xlws.FILTER(Tbl_Pool[attachEffectId], Tbl_Pool[ID] = _xlpm.CurrentPool, "無符合效果"), IF(ISERROR(_xlpm.PoolEffects), "請先完成前置選擇", _xlfn._xlws.FILTER(_xlpm.PoolEffects, (_xlpm.PoolEffects <> _xlpm.CurseSelected1) * (_xlpm.PoolEffects <> _xlpm.CurseSelected2) * (_xlfn.XLOOKUP(_xlpm.PoolEffects, Tbl_Effect[欄1], Tbl_Effect[compatibilityId], "") <> _xlpm.CurseConflict1) * (_xlfn.XLOOKUP(_xlpm.PoolEffects, Tbl_Effect[欄1], Tbl_Effect[compatibilityId], "") <> _xlpm.CurseConflict2) ) ) )} -> 無符合效果
A3: 效果池 | B3: =_xlfn.XLOOKUP($B$1, Tbl_Equip[ID], Tbl_Equip[attachEffectTableId_1]) -> 310 | C3: =_xlfn.XLOOKUP($B$1, Tbl_Equip[ID], Tbl_Equip[attachEffectTableId_2]) -> 210 | D3: =_xlfn.XLOOKUP($B$1, Tbl_Equip[ID], Tbl_Equip[attachEffectTableId_3]) -> 110 | E3: =_xlfn.XLOOKUP($B$1, Tbl_Equip[ID], Tbl_Equip[attachEffectTableId_curse1]) -> -1 | F3: =_xlfn.XLOOKUP($B$1, Tbl_Equip[ID], Tbl_Equip[attachEffectTableId_curse2]) -> -1 | G3: =_xlfn.XLOOKUP($B$1, Tbl_Equip[ID], Tbl_Equip[attachEffectTableId_curse3]) -> -1 | H3: =IF(VALUE(I3)<>0,I3&"-"&K3&" ("&J3&")","") -> 2-%null% (紅) | I3: 2 | J3: =_xlfn.IFNA(IF(I3<>0,VLOOKUP(VLOOKUP(I3,Tbl_Equip[],2,FALSE),Tbl_Color[],IFERROR(MATCH(UI!$B$1,Tbl_Color[#Headers],0),2),FALSE),""),"Unset") -> 紅 | K3: =_xlfn.IFNA(IF(I3<>0,VLOOKUP(I3,ItemText[],IFERROR(MATCH(UI!$B$1,ItemText[#Headers],0),2),FALSE),""),"Unset") -> %null% | L3: =IF(VALUE(M3)=0,"",M3&"-"&N3) -> 7000001-生命力＋２ | M3: 7000001 | N3: =IF(VALUE(M3)=0,"",VLOOKUP(VLOOKUP(M3,Tbl_Effect[],3,FALSE),EffectName[],IFERROR(MATCH(UI!$B$1,EffectName[#Headers],0),2),FALSE)) -> 生命力＋２ | O3: =IF(VALUE(P3)=0,"",P3&"-"&Q3) -> 7000001-生命力＋２ | P3: 7000001 | Q3: =IF(VALUE(P3)=0,"",VLOOKUP(VLOOKUP(P3,Tbl_Effect[],3,FALSE),EffectName[],IFERROR(MATCH(UI!$B$1,EffectName[#Headers],0),2),FALSE)) -> 生命力＋２ | R3: =IF(VALUE(S3)=0,"",S3&"-"&T3) -> 7000001-生命力＋２ | S3: 7000001 | T3: =IF(VALUE(S3)=0,"",VLOOKUP(VLOOKUP(S3,Tbl_Effect[],3,FALSE),EffectName[],IFERROR(MATCH(UI!$B$1,EffectName[#Headers],0),2),FALSE)) -> 生命力＋２ | U3: =IF(VALUE(V3)=0,"",V3&"-"&W3) | V3: 0 | W3: =IF(V3<>0,VLOOKUP(VLOOKUP(V3,Tbl_Effect[],3,FALSE),EffectName[],IFERROR(MATCH(UI!$B$1,EffectName[#Headers],0),2),FALSE),"") | X3: =IF(VALUE(Y3)=0,"",Y3&"-"&Z3) | Y3: 0 | Z3: =IF(Y3<>0,VLOOKUP(VLOOKUP(Y3,Tbl_Effect[],3,FALSE),EffectName[],IFERROR(MATCH(UI!$B$1,EffectName[#Headers],0),2),FALSE),"") | AA3: =IF(VALUE(AB3)=0,"",AB3&"-"&AC3) | AB3: 0 | AC3: =IF(AB3<>0,VLOOKUP(VLOOKUP(AB3,Tbl_Effect[],3,FALSE),EffectName[],IFERROR(MATCH(UI!$B$1,EffectName[#Headers],0),2),FALSE),"") | AE3: 7000001 | AF3: 7000001 | AG3: 7000001
A4: 效果 | B4: =IF(B3<>-1,VLOOKUP(UI!B3,L2:N2000,2,FALSE),"") -> 7000202 | C4: =IF(C3<>-1,VLOOKUP(UI!B4,O2:Q2000,2,FALSE),"") -> 7342400 | D4: =IF(D3<>-1,VLOOKUP(UI!B5,R2:T2000,2,FALSE),"") -> 7000802 | E4: =IF(E3<>-1,VLOOKUP(UI!B6,U2:W2000,2,FALSE),"") | F4: =IF(F3<>-1,VLOOKUP(UI!B7,X2:Z2000,2,FALSE),"") | G4: =IF(G3<>-1,VLOOKUP(UI!B8,AA2:AC2000,2,FALSE),"") | H4: =IF(VALUE(I4)<>0,I4&"-"&K4&" ("&J4&")","") -> 3-%null% (紅) | I4: 3 | J4: =_xlfn.IFNA(IF(I4<>0,VLOOKUP(VLOOKUP(I4,Tbl_Equip[],2,FALSE),Tbl_Color[],IFERROR(MATCH(UI!$B$1,Tbl_Color[#Headers],0),2),FALSE),""),"Unset") -> 紅 | K4: =_xlfn.IFNA(IF(I4<>0,VLOOKUP(I4,ItemText[],IFERROR(MATCH(UI!$B$1,ItemText[#Headers],0),2),FALSE),""),"Unset") -> %null% | L4: =IF(VALUE(M4)=0,"",M4&"-"&N4) -> 7000002-生命力＋３ | M4: 7000002 | N4: =IF(VALUE(M4)=0,"",VLOOKUP(VLOOKUP(M4,Tbl_Effect[],3,FALSE),EffectName[],IFERROR(MATCH(UI!$B$1,EffectName[#Headers],0),2),FALSE)) -> 生命力＋３ | O4: =IF(VALUE(P4)=0,"",P4&"-"&Q4) -> 7000002-生命力＋３ | P4: 7000002 | Q4: =IF(VALUE(P4)=0,"",VLOOKUP(VLOOKUP(P4,Tbl_Effect[],3,FALSE),EffectName[],IFERROR(MATCH(UI!$B$1,EffectName[#Headers],0),2),FALSE)) -> 生命力＋３ | R4: =IF(VALUE(S4)=0,"",S4&"-"&T4) -> 7000002-生命力＋３ | S4: 7000002 | T4: =IF(VALUE(S4)=0,"",VLOOKUP(VLOOKUP(S4,Tbl_Effect[],3,FALSE),EffectName[],IFERROR(MATCH(UI!$B$1,EffectName[#Headers],0),2),FALSE)) -> 生命力＋３ | U4: =IF(VALUE(V4)=0,"",V4&"-"&W4) | V4: 0 | W4: =IF(V4<>0,VLOOKUP(VLOOKUP(V4,Tbl_Effect[],3,FALSE),EffectName[],IFERROR(MATCH(UI!$B$1,EffectName[#Headers],0),2),FALSE),"") | X4: =IF(VALUE(Y4)=0,"",Y4&"-"&Z4) | Y4: 0 | Z4: =IF(Y4<>0,VLOOKUP(VLOOKUP(Y4,Tbl_Effect[],3,FALSE),EffectName[],IFERROR(MATCH(UI!$B$1,EffectName[#Headers],0),2),FALSE),"") | AA4: =IF(VALUE(AB4)=0,"",AB4&"-"&AC4) | AB4: 0 | AC4: =IF(AB4<>0,VLOOKUP(VLOOKUP(AB4,Tbl_Effect[],3,FALSE),EffectName[],IFERROR(MATCH(UI!$B$1,EffectName[#Headers],0),2),FALSE),"") | AE4: 7000002 | AF4: 7000002 | AG4: 7000002
H5: =IF(VALUE(I5)<>0,I5&"-"&K5&" ("&J5&")","") -> 4-%null% (紅) | I5: 4 | J5: =_xlfn.IFNA(IF(I5<>0,VLOOKUP(VLOOKUP(I5,Tbl_Equip[],2,FALSE),Tbl_Color[],IFERROR(MATCH(UI!$B$1,Tbl_Color[#Headers],0),2),FALSE),""),"Unset") -> 紅 | K5: =_xlfn.IFNA(IF(I5<>0,VLOOKUP(I5,ItemText[],IFERROR(MATCH(UI!$B$1,ItemText[#Headers],0),2),FALSE),""),"Unset") -> %null% | L5: =IF(VALUE(M5)=0,"",M5&"-"&N5) -> 7000100-集中力＋１ | M5: 7000100 | N5: =IF(VALUE(M5)=0,"",VLOOKUP(VLOOKUP(M5,Tbl_Effect[],3,FALSE),EffectName[],IFERROR(MATCH(UI!$B$1,EffectName[#Headers],0),2),FALSE)) -> 集中力＋１ | O5: =IF(VALUE(P5)=0,"",P5&"-"&Q5) -> 7000100-集中力＋１ | P5: 7000100 | Q5: =IF(VALUE(P5)=0,"",VLOOKUP(VLOOKUP(P5,Tbl_Effect[],3,FALSE),EffectName[],IFERROR(MATCH(UI!$B$1,EffectName[#Headers],0),2),FALSE)) -> 集中力＋１ | R5: =IF(VALUE(S5)=0,"",S5&"-"&T5) -> 7000100-集中力＋１ | S5: 7000100 | T5: =IF(VALUE(S5)=0,"",VLOOKUP(VLOOKUP(S5,Tbl_Effect[],3,FALSE),EffectName[],IFERROR(MATCH(UI!$B$1,EffectName[#Headers],0),2),FALSE)) -> 集中力＋１ | U5: =IF(VALUE(V5)=0,"",V5&"-"&W5) | V5: 0 | W5: =IF(V5<>0,VLOOKUP(VLOOKUP(V5,Tbl_Effect[],3,FALSE),EffectName[],IFERROR(MATCH(UI!$B$1,EffectName[#Headers],0),2),FALSE),"") | X5: =IF(VALUE(Y5)=0,"",Y5&"-"&Z5) | Y5: 0 | Z5: =IF(Y5<>0,VLOOKUP(VLOOKUP(Y5,Tbl_Effect[],3,FALSE),EffectName[],IFERROR(MATCH(UI!$B$1,EffectName[#Headers],0),2),FALSE),"") | AA5: =IF(VALUE(AB5)=0,"",AB5&"-"&AC5) | AB5: 0 | AC5: =IF(AB5<>0,VLOOKUP(VLOOKUP(AB5,Tbl_Effect[],3,FALSE),EffectName[],IFERROR(MATCH(UI!$B$1,EffectName[#Headers],0),2),FALSE),"") | AE5: 7000100 | AF5: 7000100 | AG5: 7000100
H6: =IF(VALUE(I6)<>0,I6&"-"&K6&" ("&J6&")","") -> 5-%null% (紅) | I6: 5 | J6: =_xlfn.IFNA(IF(I6<>0,VLOOKUP(VLOOKUP(I6,Tbl_Equip[],2,FALSE),Tbl_Color[],IFERROR(MATCH(UI!$B$1,Tbl_Color[#Headers],0),2),FALSE),""),"Unset") -> 紅 | K6: =_xlfn.IFNA(IF(I6<>0,VLOOKUP(I6,ItemText[],IFERROR(MATCH(UI!$B$1,ItemText[#Headers],0),2),FALSE),""),"Unset") -> %null% | L6: =IF(VALUE(M6)=0,"",M6&"-"&N6) -> 7000101-集中力＋２ | M6: 7000101 | N6: =IF(VALUE(M6)=0,"",VLOOKUP(VLOOKUP(M6,Tbl_Effect[],3,FALSE),EffectName[],IFERROR(MATCH(UI!$B$1,EffectName[#Headers],0),2),FALSE)) -> 集中力＋２ | O6: =IF(VALUE(P6)=0,"",P6&"-"&Q6) -> 7000101-集中力＋２ | P6: 7000101 | Q6: =IF(VALUE(P6)=0,"",VLOOKUP(VLOOKUP(P6,Tbl_Effect[],3,FALSE),EffectName[],IFERROR(MATCH(UI!$B$1,EffectName[#Headers],0),2),FALSE)) -> 集中力＋２ | R6: =IF(VALUE(S6)=0,"",S6&"-"&T6) -> 7000101-集中力＋２ | S6: 7000101 | T6: =IF(VALUE(S6)=0,"",VLOOKUP(VLOOKUP(S6,Tbl_Effect[],3,FALSE),EffectName[],IFERROR(MATCH(UI!$B$1,EffectName[#Headers],0),2),FALSE)) -> 集中力＋２ | U6: =IF(VALUE(V6)=0,"",V6&"-"&W6) | V6: 0 | W6: =IF(V6<>0,VLOOKUP(VLOOKUP(V6,Tbl_Effect[],3,FALSE),EffectName[],IFERROR(MATCH(UI!$B$1,EffectName[#Headers],0),2),FALSE),"") | X6: =IF(VALUE(Y6)=0,"",Y6&"-"&Z6) | Y6: 0 | Z6: =IF(Y6<>0,VLOOKUP(VLOOKUP(Y6,Tbl_Effect[],3,FALSE),EffectName[],IFERROR(MATCH(UI!$B$1,EffectName[#Headers],0),2),FALSE),"") | AA6: =IF(VALUE(AB6)=0,"",AB6&"-"&AC6) | AB6: 0 | AC6: =IF(AB6<>0,VLOOKUP(VLOOKUP(AB6,Tbl_Effect[],3,FALSE),EffectName[],IFERROR(MATCH(UI!$B$1,EffectName[#Headers],0),2),FALSE),"") | AE6: 7000101 | AF6: 7000101 | AG6: 7000101
H7: =IF(VALUE(I7)<>0,I7&"-"&K7&" ("&J7&")","") -> 6-%null% (紅) | I7: 6 | J7: =_xlfn.IFNA(IF(I7<>0,VLOOKUP(VLOOKUP(I7,Tbl_Equip[],2,FALSE),Tbl_Color[],IFERROR(MATCH(UI!$B$1,Tbl_Color[#Headers],0),2),FALSE),""),"Unset") -> 紅 | K7: =_xlfn.IFNA(IF(I7<>0,VLOOKUP(I7,ItemText[],IFERROR(MATCH(UI!$B$1,ItemText[#Headers],0),2),FALSE),""),"Unset") -> %null% | L7: =IF(VALUE(M7)=0,"",M7&"-"&N7) -> 7000102-集中力＋３ | M7: 7000102 | N7: =IF(VALUE(M7)=0,"",VLOOKUP(VLOOKUP(M7,Tbl_Effect[],3,FALSE),EffectName[],IFERROR(MATCH(UI!$B$1,EffectName[#Headers],0),2),FALSE)) -> 集中力＋３ | O7: =IF(VALUE(P7)=0,"",P7&"-"&Q7) -> 7000102-集中力＋３ | P7: 7000102 | Q7: =IF(VALUE(P7)=0,"",VLOOKUP(VLOOKUP(P7,Tbl_Effect[],3,FALSE),EffectName[],IFERROR(MATCH(UI!$B$1,EffectName[#Headers],0),2),FALSE)) -> 集中力＋３ | R7: =IF(VALUE(S7)=0,"",S7&"-"&T7) -> 7000102-集中力＋３ | S7: 7000102 | T7: =IF(VALUE(S7)=0,"",VLOOKUP(VLOOKUP(S7,Tbl_Effect[],3,FALSE),EffectName[],IFERROR(MATCH(UI!$B$1,EffectName[#Headers],0),2),FALSE)) -> 集中力＋３ | U7: =IF(VALUE(V7)=0,"",V7&"-"&W7) | V7: 0 | W7: =IF(V7<>0,VLOOKUP(VLOOKUP(V7,Tbl_Effect[],3,FALSE),EffectName[],IFERROR(MATCH(UI!$B$1,EffectName[#Headers],0),2),FALSE),"") | X7: =IF(VALUE(Y7)=0,"",Y7&"-"&Z7) | Y7: 0 | Z7: =IF(Y7<>0,VLOOKUP(VLOOKUP(Y7,Tbl_Effect[],3,FALSE),EffectName[],IFERROR(MATCH(UI!$B$1,EffectName[#Headers],0),2),FALSE),"") | AA7: =IF(VALUE(AB7)=0,"",AB7&"-"&AC7) | AB7: 0 | AC7: =IF(AB7<>0,VLOOKUP(VLOOKUP(AB7,Tbl_Effect[],3,FALSE),EffectName[],IFERROR(MATCH(UI!$B$1,EffectName[#Headers],0),2),FALSE),"") | AE7: 7000102 | AF7: 7000102 | AG7: 7000102
H8: =IF(VALUE(I8)<>0,I8&"-"&K8&" ("&J8&")","") -> 10-暗痕 (紅) | I8: 10 | J8: =_xlfn.IFNA(IF(I8<>0,VLOOKUP(VLOOKUP(I8,Tbl_Equip[],2,FALSE),Tbl_Color[],IFERROR(MATCH(UI!$B$1,Tbl_Color[#Headers],0),2),FALSE),""),"Unset") -> 紅 | K8: =_xlfn.IFNA(IF(I8<>0,VLOOKUP(I8,ItemText[],IFERROR(MATCH(UI!$B$1,ItemText[#Headers],0),2),FALSE),""),"Unset") -> 暗痕 | L8: =IF(VALUE(M8)=0,"",M8&"-"&N8) -> 7000200-耐力＋１ | M8: 7000200 | N8: =IF(VALUE(M8)=0,"",VLOOKUP(VLOOKUP(M8,Tbl_Effect[],3,FALSE),EffectName[],IFERROR(MATCH(UI!$B$1,EffectName[#Headers],0),2),FALSE)) -> 耐力＋１ | O8: =IF(VALUE(P8)=0,"",P8&"-"&Q8) -> 7000300-力氣＋１ | P8: 7000300 | Q8: =IF(VALUE(P8)=0,"",VLOOKUP(VLOOKUP(P8,Tbl_Effect[],3,FALSE),EffectName[],IFERROR(MATCH(UI!$B$1,EffectName[#Headers],0),2),FALSE)) -> 力氣＋１ | R8: =IF(VALUE(S8)=0,"",S8&"-"&T8) -> 7000300-力氣＋１ | S8: 7000300 | T8: =IF(VALUE(S8)=0,"",VLOOKUP(VLOOKUP(S8,Tbl_Effect[],3,FALSE),EffectName[],IFERROR(MATCH(UI!$B$1,EffectName[#Headers],0),2),FALSE)) -> 力氣＋１ | U8: =IF(VALUE(V8)=0,"",V8&"-"&W8) | V8: 0 | W8: =IF(V8<>0,VLOOKUP(VLOOKUP(V8,Tbl_Effect[],3,FALSE),EffectName[],IFERROR(MATCH(UI!$B$1,EffectName[#Headers],0),2),FALSE),"") | X8: =IF(VALUE(Y8)=0,"",Y8&"-"&Z8) | Y8: 0 | Z8: =IF(Y8<>0,VLOOKUP(VLOOKUP(Y8,Tbl_Effect[],3,FALSE),EffectName[],IFERROR(MATCH(UI!$B$1,EffectName[#Headers],0),2),FALSE),"") | AA8: =IF(VALUE(AB8)=0,"",AB8&"-"&AC8) | AB8: 0 | AC8: =IF(AB8<>0,VLOOKUP(VLOOKUP(AB8,Tbl_Effect[],3,FALSE),EffectName[],IFERROR(MATCH(UI!$B$1,EffectName[#Headers],0),2),FALSE),"") | AE8: 7000200 | AF8: 7000300 | AG8: 7000300
H9: =IF(VALUE(I9)<>0,I9&"-"&K9&" ("&J9&")","") -> 11-為王之證 (紅) | I9: 11 | J9: =_xlfn.IFNA(IF(I9<>0,VLOOKUP(VLOOKUP(I9,Tbl_Equip[],2,FALSE),Tbl_Color[],IFERROR(MATCH(UI!$B$1,Tbl_Color[#Headers],0),2),FALSE),""),"Unset") -> 紅 | K9: =_xlfn.IFNA(IF(I9<>0,VLOOKUP(I9,ItemText[],IFERROR(MATCH(UI!$B$1,ItemText[#Headers],0),2),FALSE),""),"Unset") -> 為王之證 | L9: =IF(VALUE(M9)=0,"",M9&"-"&N9) -> 7000201-耐力＋２ | M9: 7000201 | N9: =IF(VALUE(M9)=0,"",VLOOKUP(VLOOKUP(M9,Tbl_Effect[],3,FALSE),EffectName[],IFERROR(MATCH(UI!$B$1,EffectName[#Headers],0),2),FALSE)) -> 耐力＋２ | O9: =IF(VALUE(P9)=0,"",P9&"-"&Q9) -> 7000301-力氣＋２ | P9: 7000301 | Q9: =IF(VALUE(P9)=0,"",VLOOKUP(VLOOKUP(P9,Tbl_Effect[],3,FALSE),EffectName[],IFERROR(MATCH(UI!$B$1,EffectName[#Headers],0),2),FALSE)) -> 力氣＋２ | R9: =IF(VALUE(S9)=0,"",S9&"-"&T9) -> 7000301-力氣＋２ | S9: 7000301 | T9: =IF(VALUE(S9)=0,"",VLOOKUP(VLOOKUP(S9,Tbl_Effect[],3,FALSE),EffectName[],IFERROR(MATCH(UI!$B$1,EffectName[#Headers],0),2),FALSE)) -> 力氣＋２ | U9: =IF(VALUE(V9)=0,"",V9&"-"&W9) | V9: 0 | W9: =IF(V9<>0,VLOOKUP(VLOOKUP(V9,Tbl_Effect[],3,FALSE),EffectName[],IFERROR(MATCH(UI!$B$1,EffectName[#Headers],0),2),FALSE),"") | X9: =IF(VALUE(Y9)=0,"",Y9&"-"&Z9) | Y9: 0 | Z9: =IF(Y9<>0,VLOOKUP(VLOOKUP(Y9,Tbl_Effect[],3,FALSE),EffectName[],IFERROR(MATCH(UI!$B$1,EffectName[#Headers],0),2),FALSE),"") | AA9: =IF(VALUE(AB9)=0,"",AB9&"-"&AC9) | AB9: 0 | AC9: =IF(AB9<>0,VLOOKUP(VLOOKUP(AB9,Tbl_Effect[],3,FALSE),EffectName[],IFERROR(MATCH(UI!$B$1,EffectName[#Headers],0),2),FALSE),"") | AE9: 7000201 | AF9: 7000301 | AG9: 7000301
H10: =IF(VALUE(I10)<>0,I10&"-"&K10&" ("&J10&")","") -> 20-情景原石 (紅) | I10: 20 | J10: =_xlfn.IFNA(IF(I10<>0,VLOOKUP(VLOOKUP(I10,Tbl_Equip[],2,FALSE),Tbl_Color[],IFERROR(MATCH(UI!$B$1,Tbl_Color[#Headers],0),2),FALSE),""),"Unset") -> 紅 | K10: =_xlfn.IFNA(IF(I10<>0,VLOOKUP(I10,ItemText[],IFERROR(MATCH(UI!$B$1,ItemText[#Headers],0),2),FALSE),""),"Unset") -> 情景原石 | L10: =IF(VALUE(M10)=0,"",M10&"-"&N10) -> 7000202-耐力＋３ | M10: 7000202 | N10: =IF(VALUE(M10)=0,"",VLOOKUP(VLOOKUP(M10,Tbl_Effect[],3,FALSE),EffectName[],IFERROR(MATCH(UI!$B$1,EffectName[#Headers],0),2),FALSE)) -> 耐力＋３ | O10: =IF(VALUE(P10)=0,"",P10&"-"&Q10) -> 7000302-力氣＋３ | P10: 7000302 | Q10: =IF(VALUE(P10)=0,"",VLOOKUP(VLOOKUP(P10,Tbl_Effect[],3,FALSE),EffectName[],IFERROR(MATCH(UI!$B$1,EffectName[#Headers],0),2),FALSE)) -> 力氣＋３ | R10: =IF(VALUE(S10)=0,"",S10&"-"&T10) -> 7000302-力氣＋３ | S10: 7000302 | T10: =IF(VALUE(S10)=0,"",VLOOKUP(VLOOKUP(S10,Tbl_Effect[],3,FALSE),EffectName[],IFERROR(MATCH(UI!$B$1,EffectName[#Headers],0),2),FALSE)) -> 力氣＋３ | U10: =IF(VALUE(V10)=0,"",V10&"-"&W10) | V10: 0 | W10: =IF(V10<>0,VLOOKUP(VLOOKUP(V10,Tbl_Effect[],3,FALSE),EffectName[],IFERROR(MATCH(UI!$B$1,EffectName[#Headers],0),2),FALSE),"") | X10: =IF(VALUE(Y10)=0,"",Y10&"-"&Z10) | Y10: 0 | Z10: =IF(Y10<>0,VLOOKUP(VLOOKUP(Y10,Tbl_Effect[],3,FALSE),EffectName[],IFERROR(MATCH(UI!$B$1,EffectName[#Headers],0),2),FALSE),"") | AA10: =IF(VALUE(AB10)=0,"",AB10&"-"&AC10) | AB10: 0 | AC10: =IF(AB10<>0,VLOOKUP(VLOOKUP(AB10,Tbl_Effect[],3,FALSE),EffectName[],IFERROR(MATCH(UI!$B$1,EffectName[#Headers],0),2),FALSE),"") | AE10: 7000202 | AF10: 7000302 | AG10: 7000302
H11: =IF(VALUE(I11)<>0,I11&"-"&K11&" ("&J11&")","") -> 100-細膩的火燃情景 (紅) | I11: 100 | J11: =_xlfn.IFNA(IF(I11<>0,VLOOKUP(VLOOKUP(I11,Tbl_Equip[],2,FALSE),Tbl_Color[],IFERROR(MATCH(UI!$B$1,Tbl_Color[#Headers],0),2),FALSE),""),"Unset") -> 紅 | K11: =_xlfn.IFNA(IF(I11<>0,VLOOKUP(I11,ItemText[],IFERROR(MATCH(UI!$B$1,ItemText[#Headers],0),2),FALSE),""),"Unset") -> 細膩的火燃情景 | L11: =IF(VALUE(M11)=0,"",M11&"-"&N11) -> 7000300-力氣＋１ | M11: 7000300 | N11: =IF(VALUE(M11)=0,"",VLOOKUP(VLOOKUP(M11,Tbl_Effect[],3,FALSE),EffectName[],IFERROR(MATCH(UI!$B$1,EffectName[#Headers],0),2),FALSE)) -> 力氣＋１ | O11: =IF(VALUE(P11)=0,"",P11&"-"&Q11) -> 7000400-靈巧＋１ | P11: 7000400 | Q11: =IF(VALUE(P11)=0,"",VLOOKUP(VLOOKUP(P11,Tbl_Effect[],3,FALSE),EffectName[],IFERROR(MATCH(UI!$B$1,EffectName[#Headers],0),2),FALSE)) -> 靈巧＋１ | R11: =IF(VALUE(S11)=0,"",S11&"-"&T11) -> 7000400-靈巧＋１ | S11: 7000400 | T11: =IF(VALUE(S11)=0,"",VLOOKUP(VLOOKUP(S11,Tbl_Effect[],3,FALSE),EffectName[],IFERROR(MATCH(UI!$B$1,EffectName[#Headers],0),2),FALSE)) -> 靈巧＋１ | U11: =IF(VALUE(V11)=0,"",V11&"-"&W11) | V11: 0 | W11: =IF(V11<>0,VLOOKUP(VLOOKUP(V11,Tbl_Effect[],3,FALSE),EffectName[],IFERROR(MATCH(UI!$B$1,EffectName[#Headers],0),2),FALSE),"") | X11: =IF(VALUE(Y11)=0,"",Y11&"-"&Z11) | Y11: 0 | Z11: =IF(Y11<>0,VLOOKUP(VLOOKUP(Y11,Tbl_Effect[],3,FALSE),EffectName[],IFERROR(MATCH(UI!$B$1,EffectName[#Headers],0),2),FALSE),"") | AA11: =IF(VALUE(AB11)=0,"",AB11&"-"&AC11) | AB11: 0 | AC11: =IF(AB11<>0,VLOOKUP(VLOOKUP(AB11,Tbl_Effect[],3,FALSE),EffectName[],IFERROR(MATCH(UI!$B$1,EffectName[#Headers],0),2),FALSE),"") | AE11: 7000300 | AF11: 7000400 | AG11: 7000400
H12: =IF(VALUE(I12)<>0,I12&"-"&K12&" ("&J12&")","") -> 101-端正的火燃情景 (紅) | I12: 101 | J12: =_xlfn.IFNA(IF(I12<>0,VLOOKUP(VLOOKUP(I12,Tbl_Equip[],2,FALSE),Tbl_Color[],IFERROR(MATCH(UI!$B$1,Tbl_Color[#Headers],0),2),FALSE),""),"Unset") -> 紅 | K12: =_xlfn.IFNA(IF(I12<>0,VLOOKUP(I12,ItemText[],IFERROR(MATCH(UI!$B$1,ItemText[#Headers],0),2),FALSE),""),"Unset") -> 端正的火燃情景 | L12: =IF(VALUE(M12)=0,"",M12&"-"&N12) -> 7000301-力氣＋２ | M12: 7000301 | N12: =IF(VALUE(M12)=0,"",VLOOKUP(VLOOKUP(M12,Tbl_Effect[],3,FALSE),EffectName[],IFERROR(MATCH(UI!$B$1,EffectName[#Headers],0),2),FALSE)) -> 力氣＋２ | O12: =IF(VALUE(P12)=0,"",P12&"-"&Q12) -> 7000401-靈巧＋２ | P12: 7000401 | Q12: =IF(VALUE(P12)=0,"",VLOOKUP(VLOOKUP(P12,Tbl_Effect[],3,FALSE),EffectName[],IFERROR(MATCH(UI!$B$1,EffectName[#Headers],0),2),FALSE)) -> 靈巧＋２ | R12: =IF(VALUE(S12)=0,"",S12&"-"&T12) -> 7000401-靈巧＋２ | S12: 7000401 | T12: =IF(VALUE(S12)=0,"",VLOOKUP(VLOOKUP(S12,Tbl_Effect[],3,FALSE),EffectName[],IFERROR(MATCH(UI!$B$1,EffectName[#Headers],0),2),FALSE)) -> 靈巧＋２ | U12: =IF(VALUE(V12)=0,"",V12&"-"&W12) | V12: 0 | W12: =IF(V12<>0,VLOOKUP(VLOOKUP(V12,Tbl_Effect[],3,FALSE),EffectName[],IFERROR(MATCH(UI!$B$1,EffectName[#Headers],0),2),FALSE),"") | X12: =IF(VALUE(Y12)=0,"",Y12&"-"&Z12) | Y12: 0 | Z12: =IF(Y12<>0,VLOOKUP(VLOOKUP(Y12,Tbl_Effect[],3,FALSE),EffectName[],IFERROR(MATCH(UI!$B$1,EffectName[#Headers],0),2),FALSE),"") | AA12: =IF(VALUE(AB12)=0,"",AB12&"-"&AC12) | AB12: 0 | AC12: =IF(AB12<>0,VLOOKUP(VLOOKUP(AB12,Tbl_Effect[],3,FALSE),EffectName[],IFERROR(MATCH(UI!$B$1,EffectName[#Headers],0),2),FALSE),"") | AE12: 7000301 | AF12: 7000401 | AG12: 7000401
H13: =IF(VALUE(I13)<>0,I13&"-"&K13&" ("&J13&")","") -> 102-遼闊的火燃情景 (紅) | I13: 102 | J13: =_xlfn.IFNA(IF(I13<>0,VLOOKUP(VLOOKUP(I13,Tbl_Equip[],2,FALSE),Tbl_Color[],IFERROR(MATCH(UI!$B$1,Tbl_Color[#Headers],0),2),FALSE),""),"Unset") -> 紅 | K13: =_xlfn.IFNA(IF(I13<>0,VLOOKUP(I13,ItemText[],IFERROR(MATCH(UI!$B$1,ItemText[#Headers],0),2),FALSE),""),"Unset") -> 遼闊的火燃情景 | L13: =IF(VALUE(M13)=0,"",M13&"-"&N13) -> 7000302-力氣＋３ | M13: 7000302 | N13: =IF(VALUE(M13)=0,"",VLOOKUP(VLOOKUP(M13,Tbl_Effect[],3,FALSE),EffectName[],IFERROR(MATCH(UI!$B$1,EffectName[#Headers],0),2),FALSE)) -> 力氣＋３ | O13: =IF(VALUE(P13)=0,"",P13&"-"&Q13) -> 7000402-靈巧＋３ | P13: 7000402 | Q13: =IF(VALUE(P13)=0,"",VLOOKUP(VLOOKUP(P13,Tbl_Effect[],3,FALSE),EffectName[],IFERROR(MATCH(UI!$B$1,EffectName[#Headers],0),2),FALSE)) -> 靈巧＋３ | R13: =IF(VALUE(S13)=0,"",S13&"-"&T13) -> 7000402-靈巧＋３ | S13: 7000402 | T13: =IF(VALUE(S13)=0,"",VLOOKUP(VLOOKUP(S13,Tbl_Effect[],3,FALSE),EffectName[],IFERROR(MATCH(UI!$B$1,EffectName[#Headers],0),2),FALSE)) -> 靈巧＋３ | U13: =IF(VALUE(V13)=0,"",V13&"-"&W13) | V13: 0 | W13: =IF(V13<>0,VLOOKUP(VLOOKUP(V13,Tbl_Effect[],3,FALSE),EffectName[],IFERROR(MATCH(UI!$B$1,EffectName[#Headers],0),2),FALSE),"") | X13: =IF(VALUE(Y13)=0,"",Y13&"-"&Z13) | Y13: 0 | Z13: =IF(Y13<>0,VLOOKUP(VLOOKUP(Y13,Tbl_Effect[],3,FALSE),EffectName[],IFERROR(MATCH(UI!$B$1,EffectName[#Headers],0),2),FALSE),"") | AA13: =IF(VALUE(AB13)=0,"",AB13&"-"&AC13) | AB13: 0 | AC13: =IF(AB13<>0,VLOOKUP(VLOOKUP(AB13,Tbl_Effect[],3,FALSE),EffectName[],IFERROR(MATCH(UI!$B$1,EffectName[#Headers],0),2),FALSE),"") | AE13: 7000302 | AF13: 7000402 | AG13: 7000402
H14: =IF(VALUE(I14)<>0,I14&"-"&K14&" ("&J14&")","") -> 103-細膩的火燃情景 (紅) | I14: 103 | J14: =_xlfn.IFNA(IF(I14<>0,VLOOKUP(VLOOKUP(I14,Tbl_Equip[],2,FALSE),Tbl_Color[],IFERROR(MATCH(UI!$B$1,Tbl_Color[#Headers],0),2),FALSE),""),"Unset") -> 紅 | K14: =_xlfn.IFNA(IF(I14<>0,VLOOKUP(I14,ItemText[],IFERROR(MATCH(UI!$B$1,ItemText[#Headers],0),2),FALSE),""),"Unset") -> 細膩的火燃情景 | L14: =IF(VALUE(M14)=0,"",M14&"-"&N14) -> 7000400-靈巧＋１ | M14: 7000400 | N14: =IF(VALUE(M14)=0,"",VLOOKUP(VLOOKUP(M14,Tbl_Effect[],3,FALSE),EffectName[],IFERROR(MATCH(UI!$B$1,EffectName[#Headers],0),2),FALSE)) -> 靈巧＋１ | O14: =IF(VALUE(P14)=0,"",P14&"-"&Q14) -> 7000500-智力＋１ | P14: 7000500 | Q14: =IF(VALUE(P14)=0,"",VLOOKUP(VLOOKUP(P14,Tbl_Effect[],3,FALSE),EffectName[],IFERROR(MATCH(UI!$B$1,EffectName[#Headers],0),2),FALSE)) -> 智力＋１ | R14: =IF(VALUE(S14)=0,"",S14&"-"&T14) -> 7000500-智力＋１ | S14: 7000500 | T14: =IF(VALUE(S14)=0,"",VLOOKUP(VLOOKUP(S14,Tbl_Effect[],3,FALSE),EffectName[],IFERROR(MATCH(UI!$B$1,EffectName[#Headers],0),2),FALSE)) -> 智力＋１ | U14: =IF(VALUE(V14)=0,"",V14&"-"&W14) | V14: 0 | W14: =IF(V14<>0,VLOOKUP(VLOOKUP(V14,Tbl_Effect[],3,FALSE),EffectName[],IFERROR(MATCH(UI!$B$1,EffectName[#Headers],0),2),FALSE),"") | X14: =IF(VALUE(Y14)=0,"",Y14&"-"&Z14) | Y14: 0 | Z14: =IF(Y14<>0,VLOOKUP(VLOOKUP(Y14,Tbl_Effect[],3,FALSE),EffectName[],IFERROR(MATCH(UI!$B$1,EffectName[#Headers],0),2),FALSE),"") | AA14: =IF(VALUE(AB14)=0,"",AB14&"-"&AC14) | AB14: 0 | AC14: =IF(AB14<>0,VLOOKUP(VLOOKUP(AB14,Tbl_Effect[],3,FALSE),EffectName[],IFERROR(MATCH(UI!$B$1,EffectName[#Headers],0),2),FALSE),"") | AE14: 7000400 | AF14: 7000500 | AG14: 7000500
H15: =IF(VALUE(I15)<>0,I15&"-"&K15&" ("&J15&")","") -> 104-端正的火燃情景 (紅) | I15: 104 | J15: =_xlfn.IFNA(IF(I15<>0,VLOOKUP(VLOOKUP(I15,Tbl_Equip[],2,FALSE),Tbl_Color[],IFERROR(MATCH(UI!$B$1,Tbl_Color[#Headers],0),2),FALSE),""),"Unset") -> 紅 | K15: =_xlfn.IFNA(IF(I15<>0,VLOOKUP(I15,ItemText[],IFERROR(MATCH(UI!$B$1,ItemText[#Headers],0),2),FALSE),""),"Unset") -> 端正的火燃情景 | L15: =IF(VALUE(M15)=0,"",M15&"-"&N15) -> 7000401-靈巧＋２ | M15: 7000401 | N15: =IF(VALUE(M15)=0,"",VLOOKUP(VLOOKUP(M15,Tbl_Effect[],3,FALSE),EffectName[],IFERROR(MATCH(UI!$B$1,EffectName[#Headers],0),2),FALSE)) -> 靈巧＋２ | O15: =IF(VALUE(P15)=0,"",P15&"-"&Q15) -> 7000501-智力＋２ | P15: 7000501 | Q15: =IF(VALUE(P15)=0,"",VLOOKUP(VLOOKUP(P15,Tbl_Effect[],3,FALSE),EffectName[],IFERROR(MATCH(UI!$B$1,EffectName[#Headers],0),2),FALSE)) -> 智力＋２ | R15: =IF(VALUE(S15)=0,"",S15&"-"&T15) -> 7000501-智力＋２ | S15: 7000501 | T15: =IF(VALUE(S15)=0,"",VLOOKUP(VLOOKUP(S15,Tbl_Effect[],3,FALSE),EffectName[],IFERROR(MATCH(UI!$B$1,EffectName[#Headers],0),2),FALSE)) -> 智力＋２ | U15: =IF(VALUE(V15)=0,"",V15&"-"&W15) | V15: 0 | W15: =IF(V15<>0,VLOOKUP(VLOOKUP(V15,Tbl_Effect[],3,FALSE),EffectName[],IFERROR(MATCH(UI!$B$1,EffectName[#Headers],0),2),FALSE),"") | X15: =IF(VALUE(Y15)=0,"",Y15&"-"&Z15) | Y15: 0 | Z15: =IF(Y15<>0,VLOOKUP(VLOOKUP(Y15,Tbl_Effect[],3,FALSE),EffectName[],IFERROR(MATCH(UI!$B$1,EffectName[#Headers],0),2),FALSE),"") | AA15: =IF(VALUE(AB15)=0,"",AB15&"-"&AC15) | AB15: 0 | AC15: =IF(AB15<>0,VLOOKUP(VLOOKUP(AB15,Tbl_Effect[],3,FALSE),EffectName[],IFERROR(MATCH(UI!$B$1,EffectName[#Headers],0),2),FALSE),"") | AE15: 7000401 | AF15: 7000501 | AG15: 7000501
H16: =IF(VALUE(I16)<>0,I16&"-"&K16&" ("&J16&")","") -> 105-遼闊的火燃情景 (紅) | I16: 105 | J16: =_xlfn.IFNA(IF(I16<>0,VLOOKUP(VLOOKUP(I16,Tbl_Equip[],2,FALSE),Tbl_Color[],IFERROR(MATCH(UI!$B$1,Tbl_Color[#Headers],0),2),FALSE),""),"Unset") -> 紅 | K16: =_xlfn.IFNA(IF(I16<>0,VLOOKUP(I16,ItemText[],IFERROR(MATCH(UI!$B$1,ItemText[#Headers],0),2),FALSE),""),"Unset") -> 遼闊的火燃情景 | L16: =IF(VALUE(M16)=0,"",M16&"-"&N16) -> 7000402-靈巧＋３ | M16: 7000402 | N16: =IF(VALUE(M16)=0,"",VLOOKUP(VLOOKUP(M16,Tbl_Effect[],3,FALSE),EffectName[],IFERROR(MATCH(UI!$B$1,EffectName[#Headers],0),2),FALSE)) -> 靈巧＋３ | O16: =IF(VALUE(P16)=0,"",P16&"-"&Q16) -> 7000502-智力＋３ | P16: 7000502 | Q16: =IF(VALUE(P16)=0,"",VLOOKUP(VLOOKUP(P16,Tbl_Effect[],3,FALSE),EffectName[],IFERROR(MATCH(UI!$B$1,EffectName[#Headers],0),2),FALSE)) -> 智力＋３ | R16: =IF(VALUE(S16)=0,"",S16&"-"&T16) -> 7000502-智力＋３ | S16: 7000502 | T16: =IF(VALUE(S16)=0,"",VLOOKUP(VLOOKUP(S16,Tbl_Effect[],3,FALSE),EffectName[],IFERROR(MATCH(UI!$B$1,EffectName[#Headers],0),2),FALSE)) -> 智力＋３ | U16: =IF(VALUE(V16)=0,"",V16&"-"&W16) | V16: 0 | W16: =IF(V16<>0,VLOOKUP(VLOOKUP(V16,Tbl_Effect[],3,FALSE),EffectName[],IFERROR(MATCH(UI!$B$1,EffectName[#Headers],0),2),FALSE),"") | X16: =IF(VALUE(Y16)=0,"",Y16&"-"&Z16) | Y16: 0 | Z16: =IF(Y16<>0,VLOOKUP(VLOOKUP(Y16,Tbl_Effect[],3,FALSE),EffectName[],IFERROR(MATCH(UI!$B$1,EffectName[#Headers],0),2),FALSE),"") | AA16: =IF(VALUE(AB16)=0,"",AB16&"-"&AC16) | AB16: 0 | AC16: =IF(AB16<>0,VLOOKUP(VLOOKUP(AB16,Tbl_Effect[],3,FALSE),EffectName[],IFERROR(MATCH(UI!$B$1,EffectName[#Headers],0),2),FALSE),"") | AE16: 7000402 | AF16: 7000502 | AG16: 7000502
... H335: =IF(VALUE(I335)<>0,I335&"-"&K335&" ("&J335&")","") -> 1001220-細膩的光耀情景 (黃) | I335: 1001220 | J335: =_xlfn.IFNA(IF(I335<>0,VLOOKUP(VLOOKUP(I335,Tbl_Equip[],2,FALSE),Tbl_Color[],IFERROR(MATCH(UI!$B$1,Tbl_Color[#Headers],0),2),FALSE),""),"Unset") -> 黃 | K335: =_xlfn.IFNA(IF(I335<>0,VLOOKUP(I335,ItemText[],IFERROR(MATCH(UI!$B$1,ItemText[#Headers],0),2),FALSE),""),"Unset") -> 細膩的光耀情景 | L335: =IF(VALUE(M335)=0,"",M335&"-"&N335) -> 6632500-透過潛在能力，能比較容易找到弩 | M335: 6632500 | N335: =IF(VALUE(M335)=0,"",VLOOKUP(VLOOKUP(M335,Tbl_Effect[],3,FALSE),EffectName[],IFERROR(MATCH(UI!$B$1,EffectName[#Headers],0),2),FALSE)) -> 透過潛在能力，能比較容易找到弩 | O335: =IF(VALUE(P335)=0,"",P335&"-"&Q335) -> 6632800-透過潛在能力，能比較容易找到中盾 | P335: 6632800 | Q335: =IF(VALUE(P335)=0,"",VLOOKUP(VLOOKUP(P335,Tbl_Effect[],3,FALSE),EffectName[],IFERROR(MATCH(UI!$B$1,EffectName[#Headers],0),2),FALSE)) -> 透過潛在能力，能比較容易找到中盾 | R335: =IF(VALUE(S335)=0,"",S335&"-"&T335) -> 6647100-【執行者】提升靈巧、感應，但降低生命力 | S335: 6647100 | T335: =IF(VALUE(S335)=0,"",VLOOKUP(VLOOKUP(S335,Tbl_Effect[],3,FALSE),EffectName[],IFERROR(MATCH(UI!$B$1,EffectName[#Headers],0),2),FALSE)) -> 【執行者】提升靈巧、感應，但降低生命力 | U335: =IF(VALUE(V335)=0,"",V335&"-"&W335) | V335: 0 | W335: =IF(V335<>0,VLOOKUP(VLOOKUP(V335,Tbl_Effect[],3,FALSE),EffectName[],IFERROR(MATCH(UI!$B$1,EffectName[#Headers],0),2),FALSE),"") | X335: =IF(VALUE(Y335)=0,"",Y335&"-"&Z335) | Y335: 0 | Z335: =IF(Y335<>0,VLOOKUP(VLOOKUP(Y335,Tbl_Effect[],3,FALSE),EffectName[],IFERROR(MATCH(UI!$B$1,EffectName[#Headers],0),2),FALSE),"") | AA335: =IF(VALUE(AB335)=0,"",AB335&"-"&AC335) | AB335: 0 | AC335: =IF(AB335<>0,VLOOKUP(VLOOKUP(AB335,Tbl_Effect[],3,FALSE),EffectName[],IFERROR(MATCH(UI!$B$1,EffectName[#Headers],0),2),FALSE),"") | AE335: 6632500 | AF335: 6632800 | AG335: 6647100
H336: =IF(VALUE(I336)<>0,I336&"-"&K336&" ("&J336&")","") -> 1001221-端正的光耀情景 (黃) | I336: 1001221 | J336: =_xlfn.IFNA(IF(I336<>0,VLOOKUP(VLOOKUP(I336,Tbl_Equip[],2,FALSE),Tbl_Color[],IFERROR(MATCH(UI!$B$1,Tbl_Color[#Headers],0),2),FALSE),""),"Unset") -> 黃 | K336: =_xlfn.IFNA(IF(I336<>0,VLOOKUP(I336,ItemText[],IFERROR(MATCH(UI!$B$1,ItemText[#Headers],0),2),FALSE),""),"Unset") -> 端正的光耀情景 | L336: =IF(VALUE(M336)=0,"",M336&"-"&N336) -> 6632600-透過潛在能力，能比較容易找到弩砲 | M336: 6632600 | N336: =IF(VALUE(M336)=0,"",VLOOKUP(VLOOKUP(M336,Tbl_Effect[],3,FALSE),EffectName[],IFERROR(MATCH(UI!$B$1,EffectName[#Headers],0),2),FALSE)) -> 透過潛在能力，能比較容易找到弩砲 | O336: =IF(VALUE(P336)=0,"",P336&"-"&Q336) -> 6632900-透過潛在能力，能比較容易找到大盾 | P336: 6632900 | Q336: =IF(VALUE(P336)=0,"",VLOOKUP(VLOOKUP(P336,Tbl_Effect[],3,FALSE),EffectName[],IFERROR(MATCH(UI!$B$1,EffectName[#Headers],0),2),FALSE)) -> 透過潛在能力，能比較容易找到大盾 | R336: =IF(VALUE(S336)=0,"",S336&"-"&T336) -> #N/A | S336: #N/A | T336: =IF(VALUE(S336)=0,"",VLOOKUP(VLOOKUP(S336,Tbl_Effect[],3,FALSE),EffectName[],IFERROR(MATCH(UI!$B$1,EffectName[#Headers],0),2),FALSE)) -> #N/A | U336: =IF(VALUE(V336)=0,"",V336&"-"&W336) | V336: 0 | W336: =IF(V336<>0,VLOOKUP(VLOOKUP(V336,Tbl_Effect[],3,FALSE),EffectName[],IFERROR(MATCH(UI!$B$1,EffectName[#Headers],0),2),FALSE),"") | X336: =IF(VALUE(Y336)=0,"",Y336&"-"&Z336) | Y336: 0 | Z336: =IF(Y336<>0,VLOOKUP(VLOOKUP(Y336,Tbl_Effect[],3,FALSE),EffectName[],IFERROR(MATCH(UI!$B$1,EffectName[#Headers],0),2),FALSE),"") | AA336: =IF(VALUE(AB336)=0,"",AB336&"-"&AC336) | AB336: 0 | AC336: =IF(AB336<>0,VLOOKUP(VLOOKUP(AB336,Tbl_Effect[],3,FALSE),EffectName[],IFERROR(MATCH(UI!$B$1,EffectName[#Headers],0),2),FALSE),"") | AE336: 6632600 | AF336: 6632900 | AG336: #N/A
H337: =IF(VALUE(I337)<>0,I337&"-"&K337&" ("&J337&")","") -> 1001222-遼闊的光耀情景 (黃) | I337: 1001222 | J337: =_xlfn.IFNA(IF(I337<>0,VLOOKUP(VLOOKUP(I337,Tbl_Equip[],2,FALSE),Tbl_Color[],IFERROR(MATCH(UI!$B$1,Tbl_Color[#Headers],0),2),FALSE),""),"Unset") -> 黃 | K337: =_xlfn.IFNA(IF(I337<>0,VLOOKUP(I337,ItemText[],IFERROR(MATCH(UI!$B$1,ItemText[#Headers],0),2),FALSE),""),"Unset") -> 遼闊的光耀情景 | L337: =IF(VALUE(M337)=0,"",M337&"-"&N337) -> 6632700-透過潛在能力，能比較容易找到小盾 | M337: 6632700 | N337: =IF(VALUE(M337)=0,"",VLOOKUP(VLOOKUP(M337,Tbl_Effect[],3,FALSE),EffectName[],IFERROR(MATCH(UI!$B$1,EffectName[#Headers],0),2),FALSE)) -> 透過潛在能力，能比較容易找到小盾 | O337: =IF(VALUE(P337)=0,"",P337&"-"&Q337) -> 6633000-透過潛在能力，能比較容易找到手杖 | P337: 6633000 | Q337: =IF(VALUE(P337)=0,"",VLOOKUP(VLOOKUP(P337,Tbl_Effect[],3,FALSE),EffectName[],IFERROR(MATCH(UI!$B$1,EffectName[#Headers],0),2),FALSE)) -> 透過潛在能力，能比較容易找到手杖 | R337: =IF(VALUE(S337)=0,"",S337&"-"&T337) -> #N/A | S337: #N/A | T337: =IF(VALUE(S337)=0,"",VLOOKUP(VLOOKUP(S337,Tbl_Effect[],3,FALSE),EffectName[],IFERROR(MATCH(UI!$B$1,EffectName[#Headers],0),2),FALSE)) -> #N/A | U337: =IF(VALUE(V337)=0,"",V337&"-"&W337) | V337: 0 | W337: =IF(V337<>0,VLOOKUP(VLOOKUP(V337,Tbl_Effect[],3,FALSE),EffectName[],IFERROR(MATCH(UI!$B$1,EffectName[#Headers],0),2),FALSE),"") | X337: =IF(VALUE(Y337)=0,"",Y337&"-"&Z337) | Y337: 0 | Z337: =IF(Y337<>0,VLOOKUP(VLOOKUP(Y337,Tbl_Effect[],3,FALSE),EffectName[],IFERROR(MATCH(UI!$B$1,EffectName[#Headers],0),2),FALSE),"") | AA337: =IF(VALUE(AB337)=0,"",AB337&"-"&AC337) | AB337: 0 | AC337: =IF(AB337<>0,VLOOKUP(VLOOKUP(AB337,Tbl_Effect[],3,FALSE),EffectName[],IFERROR(MATCH(UI!$B$1,EffectName[#Headers],0),2),FALSE),"") | AE337: 6632700 | AF337: 6633000 | AG337: #N/A
H338: =IF(VALUE(I338)<>0,I338&"-"&K338&" ("&J338&")","") -> 1001300-細膩的幽靜情景 (綠) | I338: 1001300 | J338: =_xlfn.IFNA(IF(I338<>0,VLOOKUP(VLOOKUP(I338,Tbl_Equip[],2,FALSE),Tbl_Color[],IFERROR(MATCH(UI!$B$1,Tbl_Color[#Headers],0),2),FALSE),""),"Unset") -> 綠 | K338: =_xlfn.IFNA(IF(I338<>0,VLOOKUP(I338,ItemText[],IFERROR(MATCH(UI!$B$1,ItemText[#Headers],0),2),FALSE),""),"Unset") -> 細膩的幽靜情景 | L338: =IF(VALUE(M338)=0,"",M338&"-"&N338) -> 6632800-透過潛在能力，能比較容易找到中盾 | M338: 6632800 | N338: =IF(VALUE(M338)=0,"",VLOOKUP(VLOOKUP(M338,Tbl_Effect[],3,FALSE),EffectName[],IFERROR(MATCH(UI!$B$1,EffectName[#Headers],0),2),FALSE)) -> 透過潛在能力，能比較容易找到中盾 | O338: =IF(VALUE(P338)=0,"",P338&"-"&Q338) -> 6633100-透過潛在能力，能比較容易找到聖印記 | P338: 6633100 | Q338: =IF(VALUE(P338)=0,"",VLOOKUP(VLOOKUP(P338,Tbl_Effect[],3,FALSE),EffectName[],IFERROR(MATCH(UI!$B$1,EffectName[#Headers],0),2),FALSE)) -> 透過潛在能力，能比較容易找到聖印記 | R338: =IF(VALUE(S338)=0,"",S338&"-"&T338) -> #N/A | S338: #N/A | T338: =IF(VALUE(S338)=0,"",VLOOKUP(VLOOKUP(S338,Tbl_Effect[],3,FALSE),EffectName[],IFERROR(MATCH(UI!$B$1,EffectName[#Headers],0),2),FALSE)) -> #N/A | U338: =IF(VALUE(V338)=0,"",V338&"-"&W338) | V338: 0 | W338: =IF(V338<>0,VLOOKUP(VLOOKUP(V338,Tbl_Effect[],3,FALSE),EffectName[],IFERROR(MATCH(UI!$B$1,EffectName[#Headers],0),2),FALSE),"") | X338: =IF(VALUE(Y338)=0,"",Y338&"-"&Z338) | Y338: 0 | Z338: =IF(Y338<>0,VLOOKUP(VLOOKUP(Y338,Tbl_Effect[],3,FALSE),EffectName[],IFERROR(MATCH(UI!$B$1,EffectName[#Headers],0),2),FALSE),"") | AA338: =IF(VALUE(AB338)=0,"",AB338&"-"&AC338) | AB338: 0 | AC338: =IF(AB338<>0,VLOOKUP(VLOOKUP(AB338,Tbl_Effect[],3,FALSE),EffectName[],IFERROR(MATCH(UI!$B$1,EffectName[#Headers],0),2),FALSE),"") | AE338: 6632800 | AF338: 6633100 | AG338: #N/A
H339: =IF(VALUE(I339)<>0,I339&"-"&K339&" ("&J339&")","") -> 1001301-端正的幽靜情景 (綠) | I339: 1001301 | J339: =_xlfn.IFNA(IF(I339<>0,VLOOKUP(VLOOKUP(I339,Tbl_Equip[],2,FALSE),Tbl_Color[],IFERROR(MATCH(UI!$B$1,Tbl_Color[#Headers],0),2),FALSE),""),"Unset") -> 綠 | K339: =_xlfn.IFNA(IF(I339<>0,VLOOKUP(I339,ItemText[],IFERROR(MATCH(UI!$B$1,ItemText[#Headers],0),2),FALSE),""),"Unset") -> 端正的幽靜情景 | L339: =IF(VALUE(M339)=0,"",M339&"-"&N339) -> 6632900-透過潛在能力，能比較容易找到大盾 | M339: 6632900 | N339: =IF(VALUE(M339)=0,"",VLOOKUP(VLOOKUP(M339,Tbl_Effect[],3,FALSE),EffectName[],IFERROR(MATCH(UI!$B$1,EffectName[#Headers],0),2),FALSE)) -> 透過潛在能力，能比較容易找到大盾 | O339: =IF(VALUE(P339)=0,"",P339&"-"&Q339) -> 6633200-透過潛在能力，能比較容易找到火把 | P339: 6633200 | Q339: =IF(VALUE(P339)=0,"",VLOOKUP(VLOOKUP(P339,Tbl_Effect[],3,FALSE),EffectName[],IFERROR(MATCH(UI!$B$1,EffectName[#Headers],0),2),FALSE)) -> 透過潛在能力，能比較容易找到火把 | R339: =IF(VALUE(S339)=0,"",S339&"-"&T339) -> #N/A | S339: #N/A | T339: =IF(VALUE(S339)=0,"",VLOOKUP(VLOOKUP(S339,Tbl_Effect[],3,FALSE),EffectName[],IFERROR(MATCH(UI!$B$1,EffectName[#Headers],0),2),FALSE)) -> #N/A | U339: =IF(VALUE(V339)=0,"",V339&"-"&W339) | V339: 0 | W339: =IF(V339<>0,VLOOKUP(VLOOKUP(V339,Tbl_Effect[],3,FALSE),EffectName[],IFERROR(MATCH(UI!$B$1,EffectName[#Headers],0),2),FALSE),"") | X339: =IF(VALUE(Y339)=0,"",Y339&"-"&Z339) | Y339: 0 | Z339: =IF(Y339<>0,VLOOKUP(VLOOKUP(Y339,Tbl_Effect[],3,FALSE),EffectName[],IFERROR(MATCH(UI!$B$1,EffectName[#Headers],0),2),FALSE),"") | AA339: =IF(VALUE(AB339)=0,"",AB339&"-"&AC339) | AB339: 0 | AC339: =IF(AB339<>0,VLOOKUP(VLOOKUP(AB339,Tbl_Effect[],3,FALSE),EffectName[],IFERROR(MATCH(UI!$B$1,EffectName[#Headers],0),2),FALSE),"") | AE339: 6632900 | AF339: 6633200 | AG339: #N/A
H340: =IF(VALUE(I340)<>0,I340&"-"&K340&" ("&J340&")","") -> 1001302-遼闊的幽靜情景 (綠) | I340: 1001302 | J340: =_xlfn.IFNA(IF(I340<>0,VLOOKUP(VLOOKUP(I340,Tbl_Equip[],2,FALSE),Tbl_Color[],IFERROR(MATCH(UI!$B$1,Tbl_Color[#Headers],0),2),FALSE),""),"Unset") -> 綠 | K340: =_xlfn.IFNA(IF(I340<>0,VLOOKUP(I340,ItemText[],IFERROR(MATCH(UI!$B$1,ItemText[#Headers],0),2),FALSE),""),"Unset") -> 遼闊的幽靜情景 | L340: =IF(VALUE(M340)=0,"",M340&"-"&N340) -> 6633000-透過潛在能力，能比較容易找到手杖 | M340: 6633000 | N340: =IF(VALUE(M340)=0,"",VLOOKUP(VLOOKUP(M340,Tbl_Effect[],3,FALSE),EffectName[],IFERROR(MATCH(UI!$B$1,EffectName[#Headers],0),2),FALSE)) -> 透過潛在能力，能比較容易找到手杖 | O340: =IF(VALUE(P340)=0,"",P340&"-"&Q340) -> 6647200-【學者】提升集中力，但降低生命力 | P340: 6647200 | Q340: =IF(VALUE(P340)=0,"",VLOOKUP(VLOOKUP(P340,Tbl_Effect[],3,FALSE),EffectName[],IFERROR(MATCH(UI!$B$1,EffectName[#Headers],0),2),FALSE)) -> 【學者】提升集中力，但降低生命力 | R340: =IF(VALUE(S340)=0,"",S340&"-"&T340) -> #N/A | S340: #N/A | T340: =IF(VALUE(S340)=0,"",VLOOKUP(VLOOKUP(S340,Tbl_Effect[],3,FALSE),EffectName[],IFERROR(MATCH(UI!$B$1,EffectName[#Headers],0),2),FALSE)) -> #N/A | U340: =IF(VALUE(V340)=0,"",V340&"-"&W340) | V340: 0 | W340: =IF(V340<>0,VLOOKUP(VLOOKUP(V340,Tbl_Effect[],3,FALSE),EffectName[],IFERROR(MATCH(UI!$B$1,EffectName[#Headers],0),2),FALSE),"") | X340: =IF(VALUE(Y340)=0,"",Y340&"-"&Z340) | Y340: 0 | Z340: =IF(Y340<>0,VLOOKUP(VLOOKUP(Y340,Tbl_Effect[],3,FALSE),EffectName[],IFERROR(MATCH(UI!$B$1,EffectName[#Headers],0),2),FALSE),"") | AA340: =IF(VALUE(AB340)=0,"",AB340&"-"&AC340) | AB340: 0 | AC340: =IF(AB340<>0,VLOOKUP(VLOOKUP(AB340,Tbl_Effect[],3,FALSE),EffectName[],IFERROR(MATCH(UI!$B$1,EffectName[#Headers],0),2),FALSE),"") | AE340: 6633000 | AF340: 6647200 | AG340: #N/A
H341: =IF(VALUE(I341)<>0,I341&"-"&K341&" ("&J341&")","") -> 1001310-細膩的幽靜情景 (綠) | I341: 1001310 | J341: =_xlfn.IFNA(IF(I341<>0,VLOOKUP(VLOOKUP(I341,Tbl_Equip[],2,FALSE),Tbl_Color[],IFERROR(MATCH(UI!$B$1,Tbl_Color[#Headers],0),2),FALSE),""),"Unset") -> 綠 | K341: =_xlfn.IFNA(IF(I341<>0,VLOOKUP(I341,ItemText[],IFERROR(MATCH(UI!$B$1,ItemText[#Headers],0),2),FALSE),""),"Unset") -> 細膩的幽靜情景 | L341: =IF(VALUE(M341)=0,"",M341&"-"&N341) -> 6633100-透過潛在能力，能比較容易找到聖印記 | M341: 6633100 | N341: =IF(VALUE(M341)=0,"",VLOOKUP(VLOOKUP(M341,Tbl_Effect[],3,FALSE),EffectName[],IFERROR(MATCH(UI!$B$1,EffectName[#Headers],0),2),FALSE)) -> 透過潛在能力，能比較容易找到聖印記 | O341: =IF(VALUE(P341)=0,"",P341&"-"&Q341) -> 6647300-【學者】提升耐力、靈巧，但降低智力、感應 | P341: 6647300 | Q341: =IF(VALUE(P341)=0,"",VLOOKUP(VLOOKUP(P341,Tbl_Effect[],3,FALSE),EffectName[],IFERROR(MATCH(UI!$B$1,EffectName[#Headers],0),2),FALSE)) -> 【學者】提升耐力、靈巧，但降低智力、感應 | R341: =IF(VALUE(S341)=0,"",S341&"-"&T341) -> #N/A | S341: #N/A | T341: =IF(VALUE(S341)=0,"",VLOOKUP(VLOOKUP(S341,Tbl_Effect[],3,FALSE),EffectName[],IFERROR(MATCH(UI!$B$1,EffectName[#Headers],0),2),FALSE)) -> #N/A | U341: =IF(VALUE(V341)=0,"",V341&"-"&W341) | V341: 0 | W341: =IF(V341<>0,VLOOKUP(VLOOKUP(V341,Tbl_Effect[],3,FALSE),EffectName[],IFERROR(MATCH(UI!$B$1,EffectName[#Headers],0),2),FALSE),"") | X341: =IF(VALUE(Y341)=0,"",Y341&"-"&Z341) | Y341: 0 | Z341: =IF(Y341<>0,VLOOKUP(VLOOKUP(Y341,Tbl_Effect[],3,FALSE),EffectName[],IFERROR(MATCH(UI!$B$1,EffectName[#Headers],0),2),FALSE),"") | AA341: =IF(VALUE(AB341)=0,"",AB341&"-"&AC341) | AB341: 0 | AC341: =IF(AB341<>0,VLOOKUP(VLOOKUP(AB341,Tbl_Effect[],3,FALSE),EffectName[],IFERROR(MATCH(UI!$B$1,EffectName[#Headers],0),2),FALSE),"") | AE341: 6633100 | AF341: 6647300 | AG341: #N/A
H342: =IF(VALUE(I342)<>0,I342&"-"&K342&" ("&J342&")","") -> 1001311-端正的幽靜情景 (綠) | I342: 1001311 | J342: =_xlfn.IFNA(IF(I342<>0,VLOOKUP(VLOOKUP(I342,Tbl_Equip[],2,FALSE),Tbl_Color[],IFERROR(MATCH(UI!$B$1,Tbl_Color[#Headers],0),2),FALSE),""),"Unset") -> 綠 | K342: =_xlfn.IFNA(IF(I342<>0,VLOOKUP(I342,ItemText[],IFERROR(MATCH(UI!$B$1,ItemText[#Headers],0),2),FALSE),""),"Unset") -> 端正的幽靜情景 | L342: =IF(VALUE(M342)=0,"",M342&"-"&N342) -> 6633200-透過潛在能力，能比較容易找到火把 | M342: 6633200 | N342: =IF(VALUE(M342)=0,"",VLOOKUP(VLOOKUP(M342,Tbl_Effect[],3,FALSE),EffectName[],IFERROR(MATCH(UI!$B$1,EffectName[#Headers],0),2),FALSE)) -> 透過潛在能力，能比較容易找到火把 | O342: =IF(VALUE(P342)=0,"",P342&"-"&Q342) -> 6647400-【送葬者】提升靈巧，但降低生命力、信仰 | P342: 6647400 | Q342: =IF(VALUE(P342)=0,"",VLOOKUP(VLOOKUP(P342,Tbl_Effect[],3,FALSE),EffectName[],IFERROR(MATCH(UI!$B$1,EffectName[#Headers],0),2),FALSE)) -> 【送葬者】提升靈巧，但降低生命力、信仰 | R342: =IF(VALUE(S342)=0,"",S342&"-"&T342) -> #N/A | S342: #N/A | T342: =IF(VALUE(S342)=0,"",VLOOKUP(VLOOKUP(S342,Tbl_Effect[],3,FALSE),EffectName[],IFERROR(MATCH(UI!$B$1,EffectName[#Headers],0),2),FALSE)) -> #N/A | U342: =IF(VALUE(V342)=0,"",V342&"-"&W342) | V342: 0 | W342: =IF(V342<>0,VLOOKUP(VLOOKUP(V342,Tbl_Effect[],3,FALSE),EffectName[],IFERROR(MATCH(UI!$B$1,EffectName[#Headers],0),2),FALSE),"") | X342: =IF(VALUE(Y342)=0,"",Y342&"-"&Z342) | Y342: 0 | Z342: =IF(Y342<>0,VLOOKUP(VLOOKUP(Y342,Tbl_Effect[],3,FALSE),EffectName[],IFERROR(MATCH(UI!$B$1,EffectName[#Headers],0),2),FALSE),"") | AA342: =IF(VALUE(AB342)=0,"",AB342&"-"&AC342) | AB342: 0 | AC342: =IF(AB342<>0,VLOOKUP(VLOOKUP(AB342,Tbl_Effect[],3,FALSE),EffectName[],IFERROR(MATCH(UI!$B$1,EffectName[#Headers],0),2),FALSE),"") | AE342: 6633200 | AF342: 6647400 | AG342: #N/A
H343: =IF(VALUE(I343)<>0,I343&"-"&K343&" ("&J343&")","") -> 1001312-遼闊的幽靜情景 (綠) | I343: 1001312 | J343: =_xlfn.IFNA(IF(I343<>0,VLOOKUP(VLOOKUP(I343,Tbl_Equip[],2,FALSE),Tbl_Color[],IFERROR(MATCH(UI!$B$1,Tbl_Color[#Headers],0),2),FALSE),""),"Unset") -> 綠 | K343: =_xlfn.IFNA(IF(I343<>0,VLOOKUP(I343,ItemText[],IFERROR(MATCH(UI!$B$1,ItemText[#Headers],0),2),FALSE),""),"Unset") -> 遼闊的幽靜情景 | L343: =IF(VALUE(M343)=0,"",M343&"-"&N343) -> 6647200-【學者】提升集中力，但降低生命力 | M343: 6647200 | N343: =IF(VALUE(M343)=0,"",VLOOKUP(VLOOKUP(M343,Tbl_Effect[],3,FALSE),EffectName[],IFERROR(MATCH(UI!$B$1,EffectName[#Headers],0),2),FALSE)) -> 【學者】提升集中力，但降低生命力 | O343: =IF(VALUE(P343)=0,"",P343&"-"&Q343) -> 6647500-【送葬者】提升集中力、信仰，但降低力氣 | P343: 6647500 | Q343: =IF(VALUE(P343)=0,"",VLOOKUP(VLOOKUP(P343,Tbl_Effect[],3,FALSE),EffectName[],IFERROR(MATCH(UI!$B$1,EffectName[#Headers],0),2),FALSE)) -> 【送葬者】提升集中力、信仰，但降低力氣 | R343: =IF(VALUE(S343)=0,"",S343&"-"&T343) -> #N/A | S343: #N/A | T343: =IF(VALUE(S343)=0,"",VLOOKUP(VLOOKUP(S343,Tbl_Effect[],3,FALSE),EffectName[],IFERROR(MATCH(UI!$B$1,EffectName[#Headers],0),2),FALSE)) -> #N/A | U343: =IF(VALUE(V343)=0,"",V343&"-"&W343) | V343: 0 | W343: =IF(V343<>0,VLOOKUP(VLOOKUP(V343,Tbl_Effect[],3,FALSE),EffectName[],IFERROR(MATCH(UI!$B$1,EffectName[#Headers],0),2),FALSE),"") | X343: =IF(VALUE(Y343)=0,"",Y343&"-"&Z343) | Y343: 0 | Z343: =IF(Y343<>0,VLOOKUP(VLOOKUP(Y343,Tbl_Effect[],3,FALSE),EffectName[],IFERROR(MATCH(UI!$B$1,EffectName[#Headers],0),2),FALSE),"") | AA343: =IF(VALUE(AB343)=0,"",AB343&"-"&AC343) | AB343: 0 | AC343: =IF(AB343<>0,VLOOKUP(VLOOKUP(AB343,Tbl_Effect[],3,FALSE),EffectName[],IFERROR(MATCH(UI!$B$1,EffectName[#Headers],0),2),FALSE),"") | AE343: 6647200 | AF343: 6647500 | AG343: #N/A
H344: =IF(VALUE(I344)<>0,I344&"-"&K344&" ("&J344&")","") -> 1001320-細膩的幽靜情景 (綠) | I344: 1001320 | J344: =_xlfn.IFNA(IF(I344<>0,VLOOKUP(VLOOKUP(I344,Tbl_Equip[],2,FALSE),Tbl_Color[],IFERROR(MATCH(UI!$B$1,Tbl_Color[#Headers],0),2),FALSE),""),"Unset") -> 綠 | K344: =_xlfn.IFNA(IF(I344<>0,VLOOKUP(I344,ItemText[],IFERROR(MATCH(UI!$B$1,ItemText[#Headers],0),2),FALSE),""),"Unset") -> 細膩的幽靜情景 | L344: =IF(VALUE(M344)=0,"",M344&"-"&N344) -> 6647300-【學者】提升耐力、靈巧，但降低智力、感應 | M344: 6647300 | N344: =IF(VALUE(M344)=0,"",VLOOKUP(VLOOKUP(M344,Tbl_Effect[],3,FALSE),EffectName[],IFERROR(MATCH(UI!$B$1,EffectName[#Headers],0),2),FALSE)) -> 【學者】提升耐力、靈巧，但降低智力、感應 | O344: =IF(VALUE(P344)=0,"",P344&"-"&Q344) -> 6640000-【追蹤者】提升集中力，但降低生命力 | P344: 6640000 | Q344: =IF(VALUE(P344)=0,"",VLOOKUP(VLOOKUP(P344,Tbl_Effect[],3,FALSE),EffectName[],IFERROR(MATCH(UI!$B$1,EffectName[#Headers],0),2),FALSE)) -> 【追蹤者】提升集中力，但降低生命力 | R344: =IF(VALUE(S344)=0,"",S344&"-"&T344) -> #N/A | S344: #N/A | T344: =IF(VALUE(S344)=0,"",VLOOKUP(VLOOKUP(S344,Tbl_Effect[],3,FALSE),EffectName[],IFERROR(MATCH(UI!$B$1,EffectName[#Headers],0),2),FALSE)) -> #N/A | U344: =IF(VALUE(V344)=0,"",V344&"-"&W344) | V344: 0 | W344: =IF(V344<>0,VLOOKUP(VLOOKUP(V344,Tbl_Effect[],3,FALSE),EffectName[],IFERROR(MATCH(UI!$B$1,EffectName[#Headers],0),2),FALSE),"") | X344: =IF(VALUE(Y344)=0,"",Y344&"-"&Z344) | Y344: 0 | Z344: =IF(Y344<>0,VLOOKUP(VLOOKUP(Y344,Tbl_Effect[],3,FALSE),EffectName[],IFERROR(MATCH(UI!$B$1,EffectName[#Headers],0),2),FALSE),"") | AA344: =IF(VALUE(AB344)=0,"",AB344&"-"&AC344) | AB344: 0 | AC344: =IF(AB344<>0,VLOOKUP(VLOOKUP(AB344,Tbl_Effect[],3,FALSE),EffectName[],IFERROR(MATCH(UI!$B$1,EffectName[#Headers],0),2),FALSE),"") | AE344: 6647300 | AF344: 6640000 | AG344: #N/A
H345: =IF(VALUE(I345)<>0,I345&"-"&K345&" ("&J345&")","") -> 1001321-端正的幽靜情景 (綠) | I345: 1001321 | J345: =_xlfn.IFNA(IF(I345<>0,VLOOKUP(VLOOKUP(I345,Tbl_Equip[],2,FALSE),Tbl_Color[],IFERROR(MATCH(UI!$B$1,Tbl_Color[#Headers],0),2),FALSE),""),"Unset") -> 綠 | K345: =_xlfn.IFNA(IF(I345<>0,VLOOKUP(I345,ItemText[],IFERROR(MATCH(UI!$B$1,ItemText[#Headers],0),2),FALSE),""),"Unset") -> 端正的幽靜情景 | L345: =IF(VALUE(M345)=0,"",M345&"-"&N345) -> 6647400-【送葬者】提升靈巧，但降低生命力、信仰 | M345: 6647400 | N345: =IF(VALUE(M345)=0,"",VLOOKUP(VLOOKUP(M345,Tbl_Effect[],3,FALSE),EffectName[],IFERROR(MATCH(UI!$B$1,EffectName[#Headers],0),2),FALSE)) -> 【送葬者】提升靈巧，但降低生命力、信仰 | O345: =IF(VALUE(P345)=0,"",P345&"-"&Q345) -> 6640100-【追蹤者】提升智力、信仰，但降低力氣、靈巧 | P345: 6640100 | Q345: =IF(VALUE(P345)=0,"",VLOOKUP(VLOOKUP(P345,Tbl_Effect[],3,FALSE),EffectName[],IFERROR(MATCH(UI!$B$1,EffectName[#Headers],0),2),FALSE)) -> 【追蹤者】提升智力、信仰，但降低力氣、靈巧 | R345: =IF(VALUE(S345)=0,"",S345&"-"&T345) -> #N/A | S345: #N/A | T345: =IF(VALUE(S345)=0,"",VLOOKUP(VLOOKUP(S345,Tbl_Effect[],3,FALSE),EffectName[],IFERROR(MATCH(UI!$B$1,EffectName[#Headers],0),2),FALSE)) -> #N/A | U345: =IF(VALUE(V345)=0,"",V345&"-"&W345) | V345: 0 | W345: =IF(V345<>0,VLOOKUP(VLOOKUP(V345,Tbl_Effect[],3,FALSE),EffectName[],IFERROR(MATCH(UI!$B$1,EffectName[#Headers],0),2),FALSE),"") | X345: =IF(VALUE(Y345)=0,"",Y345&"-"&Z345) | Y345: 0 | Z345: =IF(Y345<>0,VLOOKUP(VLOOKUP(Y345,Tbl_Effect[],3,FALSE),EffectName[],IFERROR(MATCH(UI!$B$1,EffectName[#Headers],0),2),FALSE),"") | AA345: =IF(VALUE(AB345)=0,"",AB345&"-"&AC345) | AB345: 0 | AC345: =IF(AB345<>0,VLOOKUP(VLOOKUP(AB345,Tbl_Effect[],3,FALSE),EffectName[],IFERROR(MATCH(UI!$B$1,EffectName[#Headers],0),2),FALSE),"") | AE345: 6647400 | AF345: 6640100 | AG345: #N/A
H346: =IF(VALUE(I346)<>0,I346&"-"&K346&" ("&J346&")","") -> 1001322-遼闊的幽靜情景 (綠) | I346: 1001322 | J346: =_xlfn.IFNA(IF(I346<>0,VLOOKUP(VLOOKUP(I346,Tbl_Equip[],2,FALSE),Tbl_Color[],IFERROR(MATCH(UI!$B$1,Tbl_Color[#Headers],0),2),FALSE),""),"Unset") -> 綠 | K346: =_xlfn.IFNA(IF(I346<>0,VLOOKUP(I346,ItemText[],IFERROR(MATCH(UI!$B$1,ItemText[#Headers],0),2),FALSE),""),"Unset") -> 遼闊的幽靜情景 | L346: =IF(VALUE(M346)=0,"",M346&"-"&N346) -> 6647500-【送葬者】提升集中力、信仰，但降低力氣 | M346: 6647500 | N346: =IF(VALUE(M346)=0,"",VLOOKUP(VLOOKUP(M346,Tbl_Effect[],3,FALSE),EffectName[],IFERROR(MATCH(UI!$B$1,EffectName[#Headers],0),2),FALSE)) -> 【送葬者】提升集中力、信仰，但降低力氣 | O346: =IF(VALUE(P346)=0,"",P346&"-"&Q346) -> 6641000-【守護者】提升力氣、靈巧，但降低生命力 | P346: 6641000 | Q346: =IF(VALUE(P346)=0,"",VLOOKUP(VLOOKUP(P346,Tbl_Effect[],3,FALSE),EffectName[],IFERROR(MATCH(UI!$B$1,EffectName[#Headers],0),2),FALSE)) -> 【守護者】提升力氣、靈巧，但降低生命力 | R346: =IF(VALUE(S346)=0,"",S346&"-"&T346) -> #N/A | S346: #N/A | T346: =IF(VALUE(S346)=0,"",VLOOKUP(VLOOKUP(S346,Tbl_Effect[],3,FALSE),EffectName[],IFERROR(MATCH(UI!$B$1,EffectName[#Headers],0),2),FALSE)) -> #N/A | U346: =IF(VALUE(V346)=0,"",V346&"-"&W346) | V346: 0 | W346: =IF(V346<>0,VLOOKUP(VLOOKUP(V346,Tbl_Effect[],3,FALSE),EffectName[],IFERROR(MATCH(UI!$B$1,EffectName[#Headers],0),2),FALSE),"") | X346: =IF(VALUE(Y346)=0,"",Y346&"-"&Z346) | Y346: 0 | Z346: =IF(Y346<>0,VLOOKUP(VLOOKUP(Y346,Tbl_Effect[],3,FALSE),EffectName[],IFERROR(MATCH(UI!$B$1,EffectName[#Headers],0),2),FALSE),"") | AA346: =IF(VALUE(AB346)=0,"",AB346&"-"&AC346) | AB346: 0 | AC346: =IF(AB346<>0,VLOOKUP(VLOOKUP(AB346,Tbl_Effect[],3,FALSE),EffectName[],IFERROR(MATCH(UI!$B$1,EffectName[#Headers],0),2),FALSE),"") | AE346: 6647500 | AF346: 6641000 | AG346: #N/A
H347: =IF(VALUE(I347)<>0,I347&"-"&K347&" ("&J347&")","") -> 1002000-細膩的火燃情景 (紅) | I347: 1002000 | J347: =_xlfn.IFNA(IF(I347<>0,VLOOKUP(VLOOKUP(I347,Tbl_Equip[],2,FALSE),Tbl_Color[],IFERROR(MATCH(UI!$B$1,Tbl_Color[#Headers],0),2),FALSE),""),"Unset") -> 紅 | K347: =_xlfn.IFNA(IF(I347<>0,VLOOKUP(I347,ItemText[],IFERROR(MATCH(UI!$B$1,ItemText[#Headers],0),2),FALSE),""),"Unset") -> 細膩的火燃情景 | L347: =IF(VALUE(M347)=0,"",M347&"-"&N347) -> 6640000-【追蹤者】提升集中力，但降低生命力 | M347: 6640000 | N347: =IF(VALUE(M347)=0,"",VLOOKUP(VLOOKUP(M347,Tbl_Effect[],3,FALSE),EffectName[],IFERROR(MATCH(UI!$B$1,EffectName[#Headers],0),2),FALSE)) -> 【追蹤者】提升集中力，但降低生命力 | O347: =IF(VALUE(P347)=0,"",P347&"-"&Q347) -> 6641100-【守護者】提升集中力、信仰，但降低生命力 | P347: 6641100 | Q347: =IF(VALUE(P347)=0,"",VLOOKUP(VLOOKUP(P347,Tbl_Effect[],3,FALSE),EffectName[],IFERROR(MATCH(UI!$B$1,EffectName[#Headers],0),2),FALSE)) -> 【守護者】提升集中力、信仰，但降低生命力 | R347: =IF(VALUE(S347)=0,"",S347&"-"&T347) -> #N/A | S347: #N/A | T347: =IF(VALUE(S347)=0,"",VLOOKUP(VLOOKUP(S347,Tbl_Effect[],3,FALSE),EffectName[],IFERROR(MATCH(UI!$B$1,EffectName[#Headers],0),2),FALSE)) -> #N/A | U347: =IF(VALUE(V347)=0,"",V347&"-"&W347) | V347: 0 | W347: =IF(V347<>0,VLOOKUP(VLOOKUP(V347,Tbl_Effect[],3,FALSE),EffectName[],IFERROR(MATCH(UI!$B$1,EffectName[#Headers],0),2),FALSE),"") | X347: =IF(VALUE(Y347)=0,"",Y347&"-"&Z347) | Y347: 0 | Z347: =IF(Y347<>0,VLOOKUP(VLOOKUP(Y347,Tbl_Effect[],3,FALSE),EffectName[],IFERROR(MATCH(UI!$B$1,EffectName[#Headers],0),2),FALSE),"") | AA347: =IF(VALUE(AB347)=0,"",AB347&"-"&AC347) | AB347: 0 | AC347: =IF(AB347<>0,VLOOKUP(VLOOKUP(AB347,Tbl_Effect[],3,FALSE),EffectName[],IFERROR(MATCH(UI!$B$1,EffectName[#Headers],0),2),FALSE),"") | AE347: 6640000 | AF347: 6641100 | AG347: #N/A
... H359: =IF(VALUE(I359)<>0,I359&"-"&K359&" ("&J359&")","") -> 1002110-細膩的水滴情景 (藍) | I359: 1002110 | J359: =_xlfn.IFNA(IF(I359<>0,VLOOKUP(VLOOKUP(I359,Tbl_Equip[],2,FALSE),Tbl_Color[],IFERROR(MATCH(UI!$B$1,Tbl_Color[#Headers],0),2),FALSE),""),"Unset") -> 藍 | K359: =_xlfn.IFNA(IF(I359<>0,VLOOKUP(I359,ItemText[],IFERROR(MATCH(UI!$B$1,ItemText[#Headers],0),2),FALSE),""),"Unset") -> 細膩的水滴情景 | L359: =IF(VALUE(M359)=0,"",M359&"-"&N359) -> 6646000-【隱士】提升生命力、耐力、靈巧，但降低智力、信仰 | M359: 6646000 | N359: =IF(VALUE(M359)=0,"",VLOOKUP(VLOOKUP(M359,Tbl_Effect[],3,FALSE),EffectName[],IFERROR(MATCH(UI!$B$1,EffectName[#Headers],0),2),FALSE)) -> 【隱士】提升生命力、耐力、靈巧，但降低智力、信仰 | O359: =IF(VALUE(P359)=0,"",P359&"-"&Q359) -> 6647100-【執行者】提升靈巧、感應，但降低生命力 | P359: 6647100 | Q359: =IF(VALUE(P359)=0,"",VLOOKUP(VLOOKUP(P359,Tbl_Effect[],3,FALSE),EffectName[],IFERROR(MATCH(UI!$B$1,EffectName[#Headers],0),2),FALSE)) -> 【執行者】提升靈巧、感應，但降低生命力 | R359: =IF(VALUE(S359)=0,"",S359&"-"&T359) -> #N/A | S359: #N/A | T359: =IF(VALUE(S359)=0,"",VLOOKUP(VLOOKUP(S359,Tbl_Effect[],3,FALSE),EffectName[],IFERROR(MATCH(UI!$B$1,EffectName[#Headers],0),2),FALSE)) -> #N/A | U359: =IF(VALUE(V359)=0,"",V359&"-"&W359) | V359: 0 | W359: =IF(V359<>0,VLOOKUP(VLOOKUP(V359,Tbl_Effect[],3,FALSE),EffectName[],IFERROR(MATCH(UI!$B$1,EffectName[#Headers],0),2),FALSE),"") | X359: =IF(VALUE(Y359)=0,"",Y359&"-"&Z359) | Y359: 0 | Z359: =IF(Y359<>0,VLOOKUP(VLOOKUP(Y359,Tbl_Effect[],3,FALSE),EffectName[],IFERROR(MATCH(UI!$B$1,EffectName[#Headers],0),2),FALSE),"") | AA359: =IF(VALUE(AB359)=0,"",AB359&"-"&AC359) | AB359: 0 | AC359: =IF(AB359<>0,VLOOKUP(VLOOKUP(AB359,Tbl_Effect[],3,FALSE),EffectName[],IFERROR(MATCH(UI!$B$1,EffectName[#Headers],0),2),FALSE),"") | AE359: 6646000 | AF359: 6647100 | AG359: #N/A
H360: =IF(VALUE(I360)<>0,I360&"-"&K360&" ("&J360&")","") -> 1002111-端正的水滴情景 (藍) | I360: 1002111 | J360: =_xlfn.IFNA(IF(I360<>0,VLOOKUP(VLOOKUP(I360,Tbl_Equip[],2,FALSE),Tbl_Color[],IFERROR(MATCH(UI!$B$1,Tbl_Color[#Headers],0),2),FALSE),""),"Unset") -> 藍 | K360: =_xlfn.IFNA(IF(I360<>0,VLOOKUP(I360,ItemText[],IFERROR(MATCH(UI!$B$1,ItemText[#Headers],0),2),FALSE),""),"Unset") -> 端正的水滴情景 | L360: =IF(VALUE(M360)=0,"",M360&"-"&N360) -> 6646100-【隱士】提升智力、信仰，但降低集中力 | M360: 6646100 | N360: =IF(VALUE(M360)=0,"",VLOOKUP(VLOOKUP(M360,Tbl_Effect[],3,FALSE),EffectName[],IFERROR(MATCH(UI!$B$1,EffectName[#Headers],0),2),FALSE)) -> 【隱士】提升智力、信仰，但降低集中力 | O360: =IF(VALUE(P360)=0,"",P360&"-"&Q360) -> #N/A | P360: #N/A | Q360: =IF(VALUE(P360)=0,"",VLOOKUP(VLOOKUP(P360,Tbl_Effect[],3,FALSE),EffectName[],IFERROR(MATCH(UI!$B$1,EffectName[#Headers],0),2),FALSE)) -> #N/A | R360: =IF(VALUE(S360)=0,"",S360&"-"&T360) -> #N/A | S360: #N/A | T360: =IF(VALUE(S360)=0,"",VLOOKUP(VLOOKUP(S360,Tbl_Effect[],3,FALSE),EffectName[],IFERROR(MATCH(UI!$B$1,EffectName[#Headers],0),2),FALSE)) -> #N/A | U360: =IF(VALUE(V360)=0,"",V360&"-"&W360) | V360: 0 | W360: =IF(V360<>0,VLOOKUP(VLOOKUP(V360,Tbl_Effect[],3,FALSE),EffectName[],IFERROR(MATCH(UI!$B$1,EffectName[#Headers],0),2),FALSE),"") | X360: =IF(VALUE(Y360)=0,"",Y360&"-"&Z360) | Y360: 0 | Z360: =IF(Y360<>0,VLOOKUP(VLOOKUP(Y360,Tbl_Effect[],3,FALSE),EffectName[],IFERROR(MATCH(UI!$B$1,EffectName[#Headers],0),2),FALSE),"") | AA360: =IF(VALUE(AB360)=0,"",AB360&"-"&AC360) | AB360: 0 | AC360: =IF(AB360<>0,VLOOKUP(VLOOKUP(AB360,Tbl_Effect[],3,FALSE),EffectName[],IFERROR(MATCH(UI!$B$1,EffectName[#Headers],0),2),FALSE),"") | AE360: 6646100 | AF360: #N/A | AG360: #N/A
H361: =IF(VALUE(I361)<>0,I361&"-"&K361&" ("&J361&")","") -> 1002112-遼闊的水滴情景 (藍) | I361: 1002112 | J361: =_xlfn.IFNA(IF(I361<>0,VLOOKUP(VLOOKUP(I361,Tbl_Equip[],2,FALSE),Tbl_Color[],IFERROR(MATCH(UI!$B$1,Tbl_Color[#Headers],0),2),FALSE),""),"Unset") -> 藍 | K361: =_xlfn.IFNA(IF(I361<>0,VLOOKUP(I361,ItemText[],IFERROR(MATCH(UI!$B$1,ItemText[#Headers],0),2),FALSE),""),"Unset") -> 遼闊的水滴情景 | L361: =IF(VALUE(M361)=0,"",M361&"-"&N361) -> 6647000-【執行者】提升生命力、耐力，但降低感應 | M361: 6647000 | N361: =IF(VALUE(M361)=0,"",VLOOKUP(VLOOKUP(M361,Tbl_Effect[],3,FALSE),EffectName[],IFERROR(MATCH(UI!$B$1,EffectName[#Headers],0),2),FALSE)) -> 【執行者】提升生命力、耐力，但降低感應 | O361: =IF(VALUE(P361)=0,"",P361&"-"&Q361) -> #N/A | P361: #N/A | Q361: =IF(VALUE(P361)=0,"",VLOOKUP(VLOOKUP(P361,Tbl_Effect[],3,FALSE),EffectName[],IFERROR(MATCH(UI!$B$1,EffectName[#Headers],0),2),FALSE)) -> #N/A | R361: =IF(VALUE(S361)=0,"",S361&"-"&T361) -> #N/A | S361: #N/A | T361: =IF(VALUE(S361)=0,"",VLOOKUP(VLOOKUP(S361,Tbl_Effect[],3,FALSE),EffectName[],IFERROR(MATCH(UI!$B$1,EffectName[#Headers],0),2),FALSE)) -> #N/A | U361: =IF(VALUE(V361)=0,"",V361&"-"&W361) | V361: 0 | W361: =IF(V361<>0,VLOOKUP(VLOOKUP(V361,Tbl_Effect[],3,FALSE),EffectName[],IFERROR(MATCH(UI!$B$1,EffectName[#Headers],0),2),FALSE),"") | X361: =IF(VALUE(Y361)=0,"",Y361&"-"&Z361) | Y361: 0 | Z361: =IF(Y361<>0,VLOOKUP(VLOOKUP(Y361,Tbl_Effect[],3,FALSE),EffectName[],IFERROR(MATCH(UI!$B$1,EffectName[#Headers],0),2),FALSE),"") | AA361: =IF(VALUE(AB361)=0,"",AB361&"-"&AC361) | AB361: 0 | AC361: =IF(AB361<>0,VLOOKUP(VLOOKUP(AB361,Tbl_Effect[],3,FALSE),EffectName[],IFERROR(MATCH(UI!$B$1,EffectName[#Headers],0),2),FALSE),"") | AE361: 6647000 | AF361: #N/A | AG361: #N/A
H362: =IF(VALUE(I362)<>0,I362&"-"&K362&" ("&J362&")","") -> 1002120-細膩的水滴情景 (藍) | I362: 1002120 | J362: =_xlfn.IFNA(IF(I362<>0,VLOOKUP(VLOOKUP(I362,Tbl_Equip[],2,FALSE),Tbl_Color[],IFERROR(MATCH(UI!$B$1,Tbl_Color[#Headers],0),2),FALSE),""),"Unset") -> 藍 | K362: =_xlfn.IFNA(IF(I362<>0,VLOOKUP(I362,ItemText[],IFERROR(MATCH(UI!$B$1,ItemText[#Headers],0),2),FALSE),""),"Unset") -> 細膩的水滴情景 | L362: =IF(VALUE(M362)=0,"",M362&"-"&N362) -> 6647100-【執行者】提升靈巧、感應，但降低生命力 | M362: 6647100 | N362: =IF(VALUE(M362)=0,"",VLOOKUP(VLOOKUP(M362,Tbl_Effect[],3,FALSE),EffectName[],IFERROR(MATCH(UI!$B$1,EffectName[#Headers],0),2),FALSE)) -> 【執行者】提升靈巧、感應，但降低生命力 | O362: =IF(VALUE(P362)=0,"",P362&"-"&Q362) -> #N/A | P362: #N/A | Q362: =IF(VALUE(P362)=0,"",VLOOKUP(VLOOKUP(P362,Tbl_Effect[],3,FALSE),EffectName[],IFERROR(MATCH(UI!$B$1,EffectName[#Headers],0),2),FALSE)) -> #N/A | R362: =IF(VALUE(S362)=0,"",S362&"-"&T362) -> #N/A | S362: #N/A | T362: =IF(VALUE(S362)=0,"",VLOOKUP(VLOOKUP(S362,Tbl_Effect[],3,FALSE),EffectName[],IFERROR(MATCH(UI!$B$1,EffectName[#Headers],0),2),FALSE)) -> #N/A | U362: =IF(VALUE(V362)=0,"",V362&"-"&W362) | V362: 0 | W362: =IF(V362<>0,VLOOKUP(VLOOKUP(V362,Tbl_Effect[],3,FALSE),EffectName[],IFERROR(MATCH(UI!$B$1,EffectName[#Headers],0),2),FALSE),"") | X362: =IF(VALUE(Y362)=0,"",Y362&"-"&Z362) | Y362: 0 | Z362: =IF(Y362<>0,VLOOKUP(VLOOKUP(Y362,Tbl_Effect[],3,FALSE),EffectName[],IFERROR(MATCH(UI!$B$1,EffectName[#Headers],0),2),FALSE),"") | AA362: =IF(VALUE(AB362)=0,"",AB362&"-"&AC362) | AB362: 0 | AC362: =IF(AB362<>0,VLOOKUP(VLOOKUP(AB362,Tbl_Effect[],3,FALSE),EffectName[],IFERROR(MATCH(UI!$B$1,EffectName[#Headers],0),2),FALSE),"") | AE362: 6647100 | AF362: #N/A | AG362: #N/A
H363: =IF(VALUE(I363)<>0,I363&"-"&K363&" ("&J363&")","") -> 1002121-端正的水滴情景 (藍) | I363: 1002121 | J363: =_xlfn.IFNA(IF(I363<>0,VLOOKUP(VLOOKUP(I363,Tbl_Equip[],2,FALSE),Tbl_Color[],IFERROR(MATCH(UI!$B$1,Tbl_Color[#Headers],0),2),FALSE),""),"Unset") -> 藍 | K363: =_xlfn.IFNA(IF(I363<>0,VLOOKUP(I363,ItemText[],IFERROR(MATCH(UI!$B$1,ItemText[#Headers],0),2),FALSE),""),"Unset") -> 端正的水滴情景 | L363: =IF(VALUE(M363)=0,"",M363&"-"&N363) | M363: 0 | N363: =IF(VALUE(M363)=0,"",VLOOKUP(VLOOKUP(M363,Tbl_Effect[],3,FALSE),EffectName[],IFERROR(MATCH(UI!$B$1,EffectName[#Headers],0),2),FALSE)) | O363: =IF(VALUE(P363)=0,"",P363&"-"&Q363) | P363: 0 | Q363: =IF(VALUE(P363)=0,"",VLOOKUP(VLOOKUP(P363,Tbl_Effect[],3,FALSE),EffectName[],IFERROR(MATCH(UI!$B$1,EffectName[#Headers],0),2),FALSE)) | R363: =IF(VALUE(S363)=0,"",S363&"-"&T363) | S363: 0 | T363: =IF(VALUE(S363)=0,"",VLOOKUP(VLOOKUP(S363,Tbl_Effect[],3,FALSE),EffectName[],IFERROR(MATCH(UI!$B$1,EffectName[#Headers],0),2),FALSE)) | U363: =IF(VALUE(V363)=0,"",V363&"-"&W363) | V363: 0 | W363: =IF(V363<>0,VLOOKUP(VLOOKUP(V363,Tbl_Effect[],3,FALSE),EffectName[],IFERROR(MATCH(UI!$B$1,EffectName[#Headers],0),2),FALSE),"") | X363: =IF(VALUE(Y363)=0,"",Y363&"-"&Z363) | Y363: 0 | Z363: =IF(Y363<>0,VLOOKUP(VLOOKUP(Y363,Tbl_Effect[],3,FALSE),EffectName[],IFERROR(MATCH(UI!$B$1,EffectName[#Headers],0),2),FALSE),"") | AA363: =IF(VALUE(AB363)=0,"",AB363&"-"&AC363) | AB363: 0 | AC363: =IF(AB363<>0,VLOOKUP(VLOOKUP(AB363,Tbl_Effect[],3,FALSE),EffectName[],IFERROR(MATCH(UI!$B$1,EffectName[#Headers],0),2),FALSE),"")
H364: =IF(VALUE(I364)<>0,I364&"-"&K364&" ("&J364&")","") -> 1002122-遼闊的水滴情景 (藍) | I364: 1002122 | J364: =_xlfn.IFNA(IF(I364<>0,VLOOKUP(VLOOKUP(I364,Tbl_Equip[],2,FALSE),Tbl_Color[],IFERROR(MATCH(UI!$B$1,Tbl_Color[#Headers],0),2),FALSE),""),"Unset") -> 藍 | K364: =_xlfn.IFNA(IF(I364<>0,VLOOKUP(I364,ItemText[],IFERROR(MATCH(UI!$B$1,ItemText[#Headers],0),2),FALSE),""),"Unset") -> 遼闊的水滴情景 | L364: =IF(VALUE(M364)=0,"",M364&"-"&N364) | M364: 0 | N364: =IF(VALUE(M364)=0,"",VLOOKUP(VLOOKUP(M364,Tbl_Effect[],3,FALSE),EffectName[],IFERROR(MATCH(UI!$B$1,EffectName[#Headers],0),2),FALSE)) | O364: =IF(VALUE(P364)=0,"",P364&"-"&Q364) | P364: 0 | Q364: =IF(VALUE(P364)=0,"",VLOOKUP(VLOOKUP(P364,Tbl_Effect[],3,FALSE),EffectName[],IFERROR(MATCH(UI!$B$1,EffectName[#Headers],0),2),FALSE)) | R364: =IF(VALUE(S364)=0,"",S364&"-"&T364) | S364: 0 | T364: =IF(VALUE(S364)=0,"",VLOOKUP(VLOOKUP(S364,Tbl_Effect[],3,FALSE),EffectName[],IFERROR(MATCH(UI!$B$1,EffectName[#Headers],0),2),FALSE)) | U364: =IF(VALUE(V364)=0,"",V364&"-"&W364) | V364: 0 | W364: =IF(V364<>0,VLOOKUP(VLOOKUP(V364,Tbl_Effect[],3,FALSE),EffectName[],IFERROR(MATCH(UI!$B$1,EffectName[#Headers],0),2),FALSE),"") | X364: =IF(VALUE(Y364)=0,"",Y364&"-"&Z364) | Y364: 0 | Z364: =IF(Y364<>0,VLOOKUP(VLOOKUP(Y364,Tbl_Effect[],3,FALSE),EffectName[],IFERROR(MATCH(UI!$B$1,EffectName[#Headers],0),2),FALSE),"") | AA364: =IF(VALUE(AB364)=0,"",AB364&"-"&AC364) | AB364: 0 | AC364: =IF(AB364<>0,VLOOKUP(VLOOKUP(AB364,Tbl_Effect[],3,FALSE),EffectName[],IFERROR(MATCH(UI!$B$1,EffectName[#Headers],0),2),FALSE),"")
H365: =IF(VALUE(I365)<>0,I365&"-"&K365&" ("&J365&")","") -> 1002200-細膩的光耀情景 (黃) | I365: 1002200 | J365: =_xlfn.IFNA(IF(I365<>0,VLOOKUP(VLOOKUP(I365,Tbl_Equip[],2,FALSE),Tbl_Color[],IFERROR(MATCH(UI!$B$1,Tbl_Color[#Headers],0),2),FALSE),""),"Unset") -> 黃 | K365: =_xlfn.IFNA(IF(I365<>0,VLOOKUP(I365,ItemText[],IFERROR(MATCH(UI!$B$1,ItemText[#Headers],0),2),FALSE),""),"Unset") -> 細膩的光耀情景 | L365: =IF(VALUE(M365)=0,"",M365&"-"&N365) | M365: 0 | N365: =IF(VALUE(M365)=0,"",VLOOKUP(VLOOKUP(M365,Tbl_Effect[],3,FALSE),EffectName[],IFERROR(MATCH(UI!$B$1,EffectName[#Headers],0),2),FALSE)) | O365: =IF(VALUE(P365)=0,"",P365&"-"&Q365) | P365: 0 | Q365: =IF(VALUE(P365)=0,"",VLOOKUP(VLOOKUP(P365,Tbl_Effect[],3,FALSE),EffectName[],IFERROR(MATCH(UI!$B$1,EffectName[#Headers],0),2),FALSE)) | R365: =IF(VALUE(S365)=0,"",S365&"-"&T365) | S365: 0 | T365: =IF(VALUE(S365)=0,"",VLOOKUP(VLOOKUP(S365,Tbl_Effect[],3,FALSE),EffectName[],IFERROR(MATCH(UI!$B$1,EffectName[#Headers],0),2),FALSE)) | U365: =IF(VALUE(V365)=0,"",V365&"-"&W365) | V365: 0 | W365: =IF(V365<>0,VLOOKUP(VLOOKUP(V365,Tbl_Effect[],3,FALSE),EffectName[],IFERROR(MATCH(UI!$B$1,EffectName[#Headers],0),2),FALSE),"") | X365: =IF(VALUE(Y365)=0,"",Y365&"-"&Z365) | Y365: 0 | Z365: =IF(Y365<>0,VLOOKUP(VLOOKUP(Y365,Tbl_Effect[],3,FALSE),EffectName[],IFERROR(MATCH(UI!$B$1,EffectName[#Headers],0),2),FALSE),"") | AA365: =IF(VALUE(AB365)=0,"",AB365&"-"&AC365) | AB365: 0 | AC365: =IF(AB365<>0,VLOOKUP(VLOOKUP(AB365,Tbl_Effect[],3,FALSE),EffectName[],IFERROR(MATCH(UI!$B$1,EffectName[#Headers],0),2),FALSE),"")
H366: =IF(VALUE(I366)<>0,I366&"-"&K366&" ("&J366&")","") -> 1002201-端正的光耀情景 (黃) | I366: 1002201 | J366: =_xlfn.IFNA(IF(I366<>0,VLOOKUP(VLOOKUP(I366,Tbl_Equip[],2,FALSE),Tbl_Color[],IFERROR(MATCH(UI!$B$1,Tbl_Color[#Headers],0),2),FALSE),""),"Unset") -> 黃 | K366: =_xlfn.IFNA(IF(I366<>0,VLOOKUP(I366,ItemText[],IFERROR(MATCH(UI!$B$1,ItemText[#Headers],0),2),FALSE),""),"Unset") -> 端正的光耀情景 | L366: =IF(VALUE(M366)=0,"",M366&"-"&N366) | M366: 0 | N366: =IF(VALUE(M366)=0,"",VLOOKUP(VLOOKUP(M366,Tbl_Effect[],3,FALSE),EffectName[],IFERROR(MATCH(UI!$B$1,EffectName[#Headers],0),2),FALSE)) | O366: =IF(VALUE(P366)=0,"",P366&"-"&Q366) | P366: 0 | Q366: =IF(VALUE(P366)=0,"",VLOOKUP(VLOOKUP(P366,Tbl_Effect[],3,FALSE),EffectName[],IFERROR(MATCH(UI!$B$1,EffectName[#Headers],0),2),FALSE)) | R366: =IF(VALUE(S366)=0,"",S366&"-"&T366) | S366: 0 | T366: =IF(VALUE(S366)=0,"",VLOOKUP(VLOOKUP(S366,Tbl_Effect[],3,FALSE),EffectName[],IFERROR(MATCH(UI!$B$1,EffectName[#Headers],0),2),FALSE)) | U366: =IF(VALUE(V366)=0,"",V366&"-"&W366) | V366: 0 | W366: =IF(V366<>0,VLOOKUP(VLOOKUP(V366,Tbl_Effect[],3,FALSE),EffectName[],IFERROR(MATCH(UI!$B$1,EffectName[#Headers],0),2),FALSE),"") | X366: =IF(VALUE(Y366)=0,"",Y366&"-"&Z366) | Y366: 0 | Z366: =IF(Y366<>0,VLOOKUP(VLOOKUP(Y366,Tbl_Effect[],3,FALSE),EffectName[],IFERROR(MATCH(UI!$B$1,EffectName[#Headers],0),2),FALSE),"") | AA366: =IF(VALUE(AB366)=0,"",AB366&"-"&AC366) | AB366: 0 | AC366: =IF(AB366<>0,VLOOKUP(VLOOKUP(AB366,Tbl_Effect[],3,FALSE),EffectName[],IFERROR(MATCH(UI!$B$1,EffectName[#Headers],0),2),FALSE),"")
H367: =IF(VALUE(I367)<>0,I367&"-"&K367&" ("&J367&")","") -> 1002202-遼闊的光耀情景 (黃) | I367: 1002202 | J367: =_xlfn.IFNA(IF(I367<>0,VLOOKUP(VLOOKUP(I367,Tbl_Equip[],2,FALSE),Tbl_Color[],IFERROR(MATCH(UI!$B$1,Tbl_Color[#Headers],0),2),FALSE),""),"Unset") -> 黃 | K367: =_xlfn.IFNA(IF(I367<>0,VLOOKUP(I367,ItemText[],IFERROR(MATCH(UI!$B$1,ItemText[#Headers],0),2),FALSE),""),"Unset") -> 遼闊的光耀情景 | L367: =IF(VALUE(M367)=0,"",M367&"-"&N367) | M367: 0 | N367: =IF(VALUE(M367)=0,"",VLOOKUP(VLOOKUP(M367,Tbl_Effect[],3,FALSE),EffectName[],IFERROR(MATCH(UI!$B$1,EffectName[#Headers],0),2),FALSE)) | O367: =IF(VALUE(P367)=0,"",P367&"-"&Q367) | P367: 0 | Q367: =IF(VALUE(P367)=0,"",VLOOKUP(VLOOKUP(P367,Tbl_Effect[],3,FALSE),EffectName[],IFERROR(MATCH(UI!$B$1,EffectName[#Headers],0),2),FALSE)) | R367: =IF(VALUE(S367)=0,"",S367&"-"&T367) | S367: 0 | T367: =IF(VALUE(S367)=0,"",VLOOKUP(VLOOKUP(S367,Tbl_Effect[],3,FALSE),EffectName[],IFERROR(MATCH(UI!$B$1,EffectName[#Headers],0),2),FALSE)) | U367: =IF(VALUE(V367)=0,"",V367&"-"&W367) | V367: 0 | W367: =IF(V367<>0,VLOOKUP(VLOOKUP(V367,Tbl_Effect[],3,FALSE),EffectName[],IFERROR(MATCH(UI!$B$1,EffectName[#Headers],0),2),FALSE),"") | X367: =IF(VALUE(Y367)=0,"",Y367&"-"&Z367) | Y367: 0 | Z367: =IF(Y367<>0,VLOOKUP(VLOOKUP(Y367,Tbl_Effect[],3,FALSE),EffectName[],IFERROR(MATCH(UI!$B$1,EffectName[#Headers],0),2),FALSE),"") | AA367: =IF(VALUE(AB367)=0,"",AB367&"-"&AC367) | AB367: 0 | AC367: =IF(AB367<>0,VLOOKUP(VLOOKUP(AB367,Tbl_Effect[],3,FALSE),EffectName[],IFERROR(MATCH(UI!$B$1,EffectName[#Headers],0),2),FALSE),"")
H368: =IF(VALUE(I368)<>0,I368&"-"&K368&" ("&J368&")","") -> 1002210-細膩的光耀情景 (黃) | I368: 1002210 | J368: =_xlfn.IFNA(IF(I368<>0,VLOOKUP(VLOOKUP(I368,Tbl_Equip[],2,FALSE),Tbl_Color[],IFERROR(MATCH(UI!$B$1,Tbl_Color[#Headers],0),2),FALSE),""),"Unset") -> 黃 | K368: =_xlfn.IFNA(IF(I368<>0,VLOOKUP(I368,ItemText[],IFERROR(MATCH(UI!$B$1,ItemText[#Headers],0),2),FALSE),""),"Unset") -> 細膩的光耀情景 | L368: =IF(VALUE(M368)=0,"",M368&"-"&N368) | M368: 0 | N368: =IF(VALUE(M368)=0,"",VLOOKUP(VLOOKUP(M368,Tbl_Effect[],3,FALSE),EffectName[],IFERROR(MATCH(UI!$B$1,EffectName[#Headers],0),2),FALSE)) | O368: =IF(VALUE(P368)=0,"",P368&"-"&Q368) | P368: 0 | Q368: =IF(VALUE(P368)=0,"",VLOOKUP(VLOOKUP(P368,Tbl_Effect[],3,FALSE),EffectName[],IFERROR(MATCH(UI!$B$1,EffectName[#Headers],0),2),FALSE)) | R368: =IF(VALUE(S368)=0,"",S368&"-"&T368) | S368: 0 | T368: =IF(VALUE(S368)=0,"",VLOOKUP(VLOOKUP(S368,Tbl_Effect[],3,FALSE),EffectName[],IFERROR(MATCH(UI!$B$1,EffectName[#Headers],0),2),FALSE)) | U368: =IF(VALUE(V368)=0,"",V368&"-"&W368) | V368: 0 | W368: =IF(V368<>0,VLOOKUP(VLOOKUP(V368,Tbl_Effect[],3,FALSE),EffectName[],IFERROR(MATCH(UI!$B$1,EffectName[#Headers],0),2),FALSE),"") | X368: =IF(VALUE(Y368)=0,"",Y368&"-"&Z368) | Y368: 0 | Z368: =IF(Y368<>0,VLOOKUP(VLOOKUP(Y368,Tbl_Effect[],3,FALSE),EffectName[],IFERROR(MATCH(UI!$B$1,EffectName[#Headers],0),2),FALSE),"") | AA368: =IF(VALUE(AB368)=0,"",AB368&"-"&AC368) | AB368: 0 | AC368: =IF(AB368<>0,VLOOKUP(VLOOKUP(AB368,Tbl_Effect[],3,FALSE),EffectName[],IFERROR(MATCH(UI!$B$1,EffectName[#Headers],0),2),FALSE),"")
H369: =IF(VALUE(I369)<>0,I369&"-"&K369&" ("&J369&")","") -> 1002211-端正的光耀情景 (黃) | I369: 1002211 | J369: =_xlfn.IFNA(IF(I369<>0,VLOOKUP(VLOOKUP(I369,Tbl_Equip[],2,FALSE),Tbl_Color[],IFERROR(MATCH(UI!$B$1,Tbl_Color[#Headers],0),2),FALSE),""),"Unset") -> 黃 | K369: =_xlfn.IFNA(IF(I369<>0,VLOOKUP(I369,ItemText[],IFERROR(MATCH(UI!$B$1,ItemText[#Headers],0),2),FALSE),""),"Unset") -> 端正的光耀情景 | L369: =IF(VALUE(M369)=0,"",M369&"-"&N369) | M369: 0 | N369: =IF(VALUE(M369)=0,"",VLOOKUP(VLOOKUP(M369,Tbl_Effect[],3,FALSE),EffectName[],IFERROR(MATCH(UI!$B$1,EffectName[#Headers],0),2),FALSE)) | O369: =IF(VALUE(P369)=0,"",P369&"-"&Q369) | P369: 0 | Q369: =IF(VALUE(P369)=0,"",VLOOKUP(VLOOKUP(P369,Tbl_Effect[],3,FALSE),EffectName[],IFERROR(MATCH(UI!$B$1,EffectName[#Headers],0),2),FALSE)) | R369: =IF(VALUE(S369)=0,"",S369&"-"&T369) | S369: 0 | T369: =IF(VALUE(S369)=0,"",VLOOKUP(VLOOKUP(S369,Tbl_Effect[],3,FALSE),EffectName[],IFERROR(MATCH(UI!$B$1,EffectName[#Headers],0),2),FALSE)) | U369: =IF(VALUE(V369)=0,"",V369&"-"&W369) | V369: 0 | W369: =IF(V369<>0,VLOOKUP(VLOOKUP(V369,Tbl_Effect[],3,FALSE),EffectName[],IFERROR(MATCH(UI!$B$1,EffectName[#Headers],0),2),FALSE),"") | X369: =IF(VALUE(Y369)=0,"",Y369&"-"&Z369) | Y369: 0 | Z369: =IF(Y369<>0,VLOOKUP(VLOOKUP(Y369,Tbl_Effect[],3,FALSE),EffectName[],IFERROR(MATCH(UI!$B$1,EffectName[#Headers],0),2),FALSE),"") | AA369: =IF(VALUE(AB369)=0,"",AB369&"-"&AC369) | AB369: 0 | AC369: =IF(AB369<>0,VLOOKUP(VLOOKUP(AB369,Tbl_Effect[],3,FALSE),EffectName[],IFERROR(MATCH(UI!$B$1,EffectName[#Headers],0),2),FALSE),"")
H370: =IF(VALUE(I370)<>0,I370&"-"&K370&" ("&J370&")","") -> 1002212-遼闊的光耀情景 (黃) | I370: 1002212 | J370: =_xlfn.IFNA(IF(I370<>0,VLOOKUP(VLOOKUP(I370,Tbl_Equip[],2,FALSE),Tbl_Color[],IFERROR(MATCH(UI!$B$1,Tbl_Color[#Headers],0),2),FALSE),""),"Unset") -> 黃 | K370: =_xlfn.IFNA(IF(I370<>0,VLOOKUP(I370,ItemText[],IFERROR(MATCH(UI!$B$1,ItemText[#Headers],0),2),FALSE),""),"Unset") -> 遼闊的光耀情景 | L370: =IF(VALUE(M370)=0,"",M370&"-"&N370) | M370: 0 | N370: =IF(VALUE(M370)=0,"",VLOOKUP(VLOOKUP(M370,Tbl_Effect[],3,FALSE),EffectName[],IFERROR(MATCH(UI!$B$1,EffectName[#Headers],0),2),FALSE)) | O370: =IF(VALUE(P370)=0,"",P370&"-"&Q370) | P370: 0 | Q370: =IF(VALUE(P370)=0,"",VLOOKUP(VLOOKUP(P370,Tbl_Effect[],3,FALSE),EffectName[],IFERROR(MATCH(UI!$B$1,EffectName[#Headers],0),2),FALSE)) | R370: =IF(VALUE(S370)=0,"",S370&"-"&T370) | S370: 0 | T370: =IF(VALUE(S370)=0,"",VLOOKUP(VLOOKUP(S370,Tbl_Effect[],3,FALSE),EffectName[],IFERROR(MATCH(UI!$B$1,EffectName[#Headers],0),2),FALSE)) | U370: =IF(VALUE(V370)=0,"",V370&"-"&W370) | V370: 0 | W370: =IF(V370<>0,VLOOKUP(VLOOKUP(V370,Tbl_Effect[],3,FALSE),EffectName[],IFERROR(MATCH(UI!$B$1,EffectName[#Headers],0),2),FALSE),"") | X370: =IF(VALUE(Y370)=0,"",Y370&"-"&Z370) | Y370: 0 | Z370: =IF(Y370<>0,VLOOKUP(VLOOKUP(Y370,Tbl_Effect[],3,FALSE),EffectName[],IFERROR(MATCH(UI!$B$1,EffectName[#Headers],0),2),FALSE),"") | AA370: =IF(VALUE(AB370)=0,"",AB370&"-"&AC370) | AB370: 0 | AC370: =IF(AB370<>0,VLOOKUP(VLOOKUP(AB370,Tbl_Effect[],3,FALSE),EffectName[],IFERROR(MATCH(UI!$B$1,EffectName[#Headers],0),2),FALSE),"")
H371: =IF(VALUE(I371)<>0,I371&"-"&K371&" ("&J371&")","") -> 1002220-細膩的光耀情景 (黃) | I371: 1002220 | J371: =_xlfn.IFNA(IF(I371<>0,VLOOKUP(VLOOKUP(I371,Tbl_Equip[],2,FALSE),Tbl_Color[],IFERROR(MATCH(UI!$B$1,Tbl_Color[#Headers],0),2),FALSE),""),"Unset") -> 黃 | K371: =_xlfn.IFNA(IF(I371<>0,VLOOKUP(I371,ItemText[],IFERROR(MATCH(UI!$B$1,ItemText[#Headers],0),2),FALSE),""),"Unset") -> 細膩的光耀情景 | L371: =IF(VALUE(M371)=0,"",M371&"-"&N371) | M371: 0 | N371: =IF(VALUE(M371)=0,"",VLOOKUP(VLOOKUP(M371,Tbl_Effect[],3,FALSE),EffectName[],IFERROR(MATCH(UI!$B$1,EffectName[#Headers],0),2),FALSE)) | O371: =IF(VALUE(P371)=0,"",P371&"-"&Q371) | P371: 0 | Q371: =IF(VALUE(P371)=0,"",VLOOKUP(VLOOKUP(P371,Tbl_Effect[],3,FALSE),EffectName[],IFERROR(MATCH(UI!$B$1,EffectName[#Headers],0),2),FALSE)) | R371: =IF(VALUE(S371)=0,"",S371&"-"&T371) | S371: 0 | T371: =IF(VALUE(S371)=0,"",VLOOKUP(VLOOKUP(S371,Tbl_Effect[],3,FALSE),EffectName[],IFERROR(MATCH(UI!$B$1,EffectName[#Headers],0),2),FALSE)) | U371: =IF(VALUE(V371)=0,"",V371&"-"&W371) | V371: 0 | W371: =IF(V371<>0,VLOOKUP(VLOOKUP(V371,Tbl_Effect[],3,FALSE),EffectName[],IFERROR(MATCH(UI!$B$1,EffectName[#Headers],0),2),FALSE),"") | X371: =IF(VALUE(Y371)=0,"",Y371&"-"&Z371) | Y371: 0 | Z371: =IF(Y371<>0,VLOOKUP(VLOOKUP(Y371,Tbl_Effect[],3,FALSE),EffectName[],IFERROR(MATCH(UI!$B$1,EffectName[#Headers],0),2),FALSE),"") | AA371: =IF(VALUE(AB371)=0,"",AB371&"-"&AC371) | AB371: 0 | AC371: =IF(AB371<>0,VLOOKUP(VLOOKUP(AB371,Tbl_Effect[],3,FALSE),EffectName[],IFERROR(MATCH(UI!$B$1,EffectName[#Headers],0),2),FALSE),"")
H372: =IF(VALUE(I372)<>0,I372&"-"&K372&" ("&J372&")","") -> 1002221-端正的光耀情景 (黃) | I372: 1002221 | J372: =_xlfn.IFNA(IF(I372<>0,VLOOKUP(VLOOKUP(I372,Tbl_Equip[],2,FALSE),Tbl_Color[],IFERROR(MATCH(UI!$B$1,Tbl_Color[#Headers],0),2),FALSE),""),"Unset") -> 黃 | K372: =_xlfn.IFNA(IF(I372<>0,VLOOKUP(I372,ItemText[],IFERROR(MATCH(UI!$B$1,ItemText[#Headers],0),2),FALSE),""),"Unset") -> 端正的光耀情景 | L372: =IF(VALUE(M372)=0,"",M372&"-"&N372) | M372: 0 | N372: =IF(VALUE(M372)=0,"",VLOOKUP(VLOOKUP(M372,Tbl_Effect[],3,FALSE),EffectName[],IFERROR(MATCH(UI!$B$1,EffectName[#Headers],0),2),FALSE)) | O372: =IF(VALUE(P372)=0,"",P372&"-"&Q372) | P372: 0 | Q372: =IF(VALUE(P372)=0,"",VLOOKUP(VLOOKUP(P372,Tbl_Effect[],3,FALSE),EffectName[],IFERROR(MATCH(UI!$B$1,EffectName[#Headers],0),2),FALSE)) | R372: =IF(VALUE(S372)=0,"",S372&"-"&T372) | S372: 0 | T372: =IF(VALUE(S372)=0,"",VLOOKUP(VLOOKUP(S372,Tbl_Effect[],3,FALSE),EffectName[],IFERROR(MATCH(UI!$B$1,EffectName[#Headers],0),2),FALSE)) | U372: =IF(VALUE(V372)=0,"",V372&"-"&W372) | V372: 0 | W372: =IF(V372<>0,VLOOKUP(VLOOKUP(V372,Tbl_Effect[],3,FALSE),EffectName[],IFERROR(MATCH(UI!$B$1,EffectName[#Headers],0),2),FALSE),"") | X372: =IF(VALUE(Y372)=0,"",Y372&"-"&Z372) | Y372: 0 | Z372: =IF(Y372<>0,VLOOKUP(VLOOKUP(Y372,Tbl_Effect[],3,FALSE),EffectName[],IFERROR(MATCH(UI!$B$1,EffectName[#Headers],0),2),FALSE),"") | AA372: =IF(VALUE(AB372)=0,"",AB372&"-"&AC372) | AB372: 0 | AC372: =IF(AB372<>0,VLOOKUP(VLOOKUP(AB372,Tbl_Effect[],3,FALSE),EffectName[],IFERROR(MATCH(UI!$B$1,EffectName[#Headers],0),2),FALSE),"")
H373: =IF(VALUE(I373)<>0,I373&"-"&K373&" ("&J373&")","") -> 1002222-遼闊的光耀情景 (黃) | I373: 1002222 | J373: =_xlfn.IFNA(IF(I373<>0,VLOOKUP(VLOOKUP(I373,Tbl_Equip[],2,FALSE),Tbl_Color[],IFERROR(MATCH(UI!$B$1,Tbl_Color[#Headers],0),2),FALSE),""),"Unset") -> 黃 | K373: =_xlfn.IFNA(IF(I373<>0,VLOOKUP(I373,ItemText[],IFERROR(MATCH(UI!$B$1,ItemText[#Headers],0),2),FALSE),""),"Unset") -> 遼闊的光耀情景 | L373: =IF(VALUE(M373)=0,"",M373&"-"&N373) | M373: 0 | N373: =IF(VALUE(M373)=0,"",VLOOKUP(VLOOKUP(M373,Tbl_Effect[],3,FALSE),EffectName[],IFERROR(MATCH(UI!$B$1,EffectName[#Headers],0),2),FALSE)) | O373: =IF(VALUE(P373)=0,"",P373&"-"&Q373) | P373: 0 | Q373: =IF(VALUE(P373)=0,"",VLOOKUP(VLOOKUP(P373,Tbl_Effect[],3,FALSE),EffectName[],IFERROR(MATCH(UI!$B$1,EffectName[#Headers],0),2),FALSE)) | R373: =IF(VALUE(S373)=0,"",S373&"-"&T373) | S373: 0 | T373: =IF(VALUE(S373)=0,"",VLOOKUP(VLOOKUP(S373,Tbl_Effect[],3,FALSE),EffectName[],IFERROR(MATCH(UI!$B$1,EffectName[#Headers],0),2),FALSE)) | U373: =IF(VALUE(V373)=0,"",V373&"-"&W373) | V373: 0 | W373: =IF(V373<>0,VLOOKUP(VLOOKUP(V373,Tbl_Effect[],3,FALSE),EffectName[],IFERROR(MATCH(UI!$B$1,EffectName[#Headers],0),2),FALSE),"") | X373: =IF(VALUE(Y373)=0,"",Y373&"-"&Z373) | Y373: 0 | Z373: =IF(Y373<>0,VLOOKUP(VLOOKUP(Y373,Tbl_Effect[],3,FALSE),EffectName[],IFERROR(MATCH(UI!$B$1,EffectName[#Headers],0),2),FALSE),"") | AA373: =IF(VALUE(AB373)=0,"",AB373&"-"&AC373) | AB373: 0 | AC373: =IF(AB373<>0,VLOOKUP(VLOOKUP(AB373,Tbl_Effect[],3,FALSE),EffectName[],IFERROR(MATCH(UI!$B$1,EffectName[#Headers],0),2),FALSE),"")
H374: =IF(VALUE(I374)<>0,I374&"-"&K374&" ("&J374&")","") -> 1002300-細膩的幽靜情景 (綠) | I374: 1002300 | J374: =_xlfn.IFNA(IF(I374<>0,VLOOKUP(VLOOKUP(I374,Tbl_Equip[],2,FALSE),Tbl_Color[],IFERROR(MATCH(UI!$B$1,Tbl_Color[#Headers],0),2),FALSE),""),"Unset") -> 綠 | K374: =_xlfn.IFNA(IF(I374<>0,VLOOKUP(I374,ItemText[],IFERROR(MATCH(UI!$B$1,ItemText[#Headers],0),2),FALSE),""),"Unset") -> 細膩的幽靜情景 | L374: =IF(VALUE(M374)=0,"",M374&"-"&N374) | M374: 0 | N374: =IF(VALUE(M374)=0,"",VLOOKUP(VLOOKUP(M374,Tbl_Effect[],3,FALSE),EffectName[],IFERROR(MATCH(UI!$B$1,EffectName[#Headers],0),2),FALSE)) | O374: =IF(VALUE(P374)=0,"",P374&"-"&Q374) | P374: 0 | Q374: =IF(VALUE(P374)=0,"",VLOOKUP(VLOOKUP(P374,Tbl_Effect[],3,FALSE),EffectName[],IFERROR(MATCH(UI!$B$1,EffectName[#Headers],0),2),FALSE)) | R374: =IF(VALUE(S374)=0,"",S374&"-"&T374) | S374: 0 | T374: =IF(VALUE(S374)=0,"",VLOOKUP(VLOOKUP(S374,Tbl_Effect[],3,FALSE),EffectName[],IFERROR(MATCH(UI!$B$1,EffectName[#Headers],0),2),FALSE)) | U374: =IF(VALUE(V374)=0,"",V374&"-"&W374) | V374: 0 | W374: =IF(V374<>0,VLOOKUP(VLOOKUP(V374,Tbl_Effect[],3,FALSE),EffectName[],IFERROR(MATCH(UI!$B$1,EffectName[#Headers],0),2),FALSE),"") | X374: =IF(VALUE(Y374)=0,"",Y374&"-"&Z374) | Y374: 0 | Z374: =IF(Y374<>0,VLOOKUP(VLOOKUP(Y374,Tbl_Effect[],3,FALSE),EffectName[],IFERROR(MATCH(UI!$B$1,EffectName[#Headers],0),2),FALSE),"") | AA374: =IF(VALUE(AB374)=0,"",AB374&"-"&AC374) | AB374: 0 | AC374: =IF(AB374<>0,VLOOKUP(VLOOKUP(AB374,Tbl_Effect[],3,FALSE),EffectName[],IFERROR(MATCH(UI!$B$1,EffectName[#Headers],0),2),FALSE),"")
... H1386: =IF(VALUE(I1386)<>0,I1386&"-"&K1386&" ("&J1386&")","") -> 7999999-Unset (紅) | I1386: 7999999 | J1386: =_xlfn.IFNA(IF(I1386<>0,VLOOKUP(VLOOKUP(I1386,Tbl_Equip[],2,FALSE),Tbl_Color[],IFERROR(MATCH(UI!$B$1,Tbl_Color[#Headers],0),2),FALSE),""),"Unset") -> 紅 | K1386: =_xlfn.IFNA(IF(I1386<>0,VLOOKUP(I1386,ItemText[],IFERROR(MATCH(UI!$B$1,ItemText[#Headers],0),2),FALSE),""),"Unset") -> Unset | L1386: =IF(VALUE(M1386)=0,"",M1386&"-"&N1386) | M1386: 0 | N1386: =IF(VALUE(M1386)=0,"",VLOOKUP(VLOOKUP(M1386,Tbl_Effect[],3,FALSE),EffectName[],IFERROR(MATCH(UI!$B$1,EffectName[#Headers],0),2),FALSE)) | O1386: =IF(VALUE(P1386)=0,"",P1386&"-"&Q1386) | P1386: 0 | Q1386: =IF(VALUE(P1386)=0,"",VLOOKUP(VLOOKUP(P1386,Tbl_Effect[],3,FALSE),EffectName[],IFERROR(MATCH(UI!$B$1,EffectName[#Headers],0),2),FALSE)) | R1386: =IF(VALUE(S1386)=0,"",S1386&"-"&T1386) | S1386: 0 | T1386: =IF(VALUE(S1386)=0,"",VLOOKUP(VLOOKUP(S1386,Tbl_Effect[],3,FALSE),EffectName[],IFERROR(MATCH(UI!$B$1,EffectName[#Headers],0),2),FALSE)) | U1386: =IF(VALUE(V1386)=0,"",V1386&"-"&W1386) | V1386: 0 | W1386: =IF(V1386<>0,VLOOKUP(VLOOKUP(V1386,Tbl_Effect[],3,FALSE),EffectName[],IFERROR(MATCH(UI!$B$1,EffectName[#Headers],0),2),FALSE),"") | X1386: =IF(VALUE(Y1386)=0,"",Y1386&"-"&Z1386) | Y1386: 0 | Z1386: =IF(Y1386<>0,VLOOKUP(VLOOKUP(Y1386,Tbl_Effect[],3,FALSE),EffectName[],IFERROR(MATCH(UI!$B$1,EffectName[#Headers],0),2),FALSE),"") | AA1386: =IF(VALUE(AB1386)=0,"",AB1386&"-"&AC1386) | AB1386: 0 | AC1386: =IF(AB1386<>0,VLOOKUP(VLOOKUP(AB1386,Tbl_Effect[],3,FALSE),EffectName[],IFERROR(MATCH(UI!$B$1,EffectName[#Headers],0),2),FALSE),"")
H1387: =IF(VALUE(I1387)<>0,I1387&"-"&K1387&" ("&J1387&")","") | I1387: 0 | J1387: =_xlfn.IFNA(IF(I1387<>0,VLOOKUP(VLOOKUP(I1387,Tbl_Equip[],2,FALSE),Tbl_Color[],IFERROR(MATCH(UI!$B$1,Tbl_Color[#Headers],0),2),FALSE),""),"Unset") | K1387: =_xlfn.IFNA(IF(I1387<>0,VLOOKUP(I1387,ItemText[],IFERROR(MATCH(UI!$B$1,ItemText[#Headers],0),2),FALSE),""),"Unset") | M1387: 0 | P1387: 0 | S1387: 0 | T1387: =IF(VALUE(S1387)=0,"",VLOOKUP(VLOOKUP(S1387,Tbl_Effect[],3,FALSE),EffectName[],IFERROR(MATCH(UI!$B$1,EffectName[#Headers],0),2),FALSE)) | U1387: =IF(VALUE(V1387)=0,"",V1387&"-"&W1387) | V1387: 0 | W1387: =IF(V1387<>0,VLOOKUP(VLOOKUP(V1387,Tbl_Effect[],3,FALSE),EffectName[],IFERROR(MATCH(UI!$B$1,EffectName[#Headers],0),2),FALSE),"") | X1387: =IF(VALUE(Y1387)=0,"",Y1387&"-"&Z1387) | Y1387: 0 | Z1387: =IF(Y1387<>0,VLOOKUP(VLOOKUP(Y1387,Tbl_Effect[],3,FALSE),EffectName[],IFERROR(MATCH(UI!$B$1,EffectName[#Headers],0),2),FALSE),"") | AA1387: =IF(VALUE(AB1387)=0,"",AB1387&"-"&AC1387) | AB1387: 0 | AC1387: =IF(AB1387<>0,VLOOKUP(VLOOKUP(AB1387,Tbl_Effect[],3,FALSE),EffectName[],IFERROR(MATCH(UI!$B$1,EffectName[#Headers],0),2),FALSE),"")
H1388: =IF(VALUE(I1388)<>0,I1388&"-"&K1388&" ("&J1388&")","") | I1388: 0 | J1388: =_xlfn.IFNA(IF(I1388<>0,VLOOKUP(VLOOKUP(I1388,Tbl_Equip[],2,FALSE),Tbl_Color[],IFERROR(MATCH(UI!$B$1,Tbl_Color[#Headers],0),2),FALSE),""),"Unset") | K1388: =_xlfn.IFNA(IF(I1388<>0,VLOOKUP(I1388,ItemText[],IFERROR(MATCH(UI!$B$1,ItemText[#Headers],0),2),FALSE),""),"Unset") | M1388: 0 | P1388: 0 | S1388: 0 | T1388: =IF(VALUE(S1388)=0,"",VLOOKUP(VLOOKUP(S1388,Tbl_Effect[],3,FALSE),EffectName[],IFERROR(MATCH(UI!$B$1,EffectName[#Headers],0),2),FALSE)) | U1388: =IF(VALUE(V1388)=0,"",V1388&"-"&W1388) | V1388: 0 | W1388: =IF(V1388<>0,VLOOKUP(VLOOKUP(V1388,Tbl_Effect[],3,FALSE),EffectName[],IFERROR(MATCH(UI!$B$1,EffectName[#Headers],0),2),FALSE),"") | X1388: =IF(VALUE(Y1388)=0,"",Y1388&"-"&Z1388) | Y1388: 0 | Z1388: =IF(Y1388<>0,VLOOKUP(VLOOKUP(Y1388,Tbl_Effect[],3,FALSE),EffectName[],IFERROR(MATCH(UI!$B$1,EffectName[#Headers],0),2),FALSE),"") | AA1388: =IF(VALUE(AB1388)=0,"",AB1388&"-"&AC1388) | AB1388: 0 | AC1388: =IF(AB1388<>0,VLOOKUP(VLOOKUP(AB1388,Tbl_Effect[],3,FALSE),EffectName[],IFERROR(MATCH(UI!$B$1,EffectName[#Headers],0),2),FALSE),"")
H1389: =IF(VALUE(I1389)<>0,I1389&"-"&K1389&" ("&J1389&")","") | I1389: 0 | J1389: =_xlfn.IFNA(IF(I1389<>0,VLOOKUP(VLOOKUP(I1389,Tbl_Equip[],2,FALSE),Tbl_Color[],IFERROR(MATCH(UI!$B$1,Tbl_Color[#Headers],0),2),FALSE),""),"Unset") | K1389: =_xlfn.IFNA(IF(I1389<>0,VLOOKUP(I1389,ItemText[],IFERROR(MATCH(UI!$B$1,ItemText[#Headers],0),2),FALSE),""),"Unset") | M1389: 0 | P1389: 0 | S1389: 0 | T1389: =IF(VALUE(S1389)=0,"",VLOOKUP(VLOOKUP(S1389,Tbl_Effect[],3,FALSE),EffectName[],IFERROR(MATCH(UI!$B$1,EffectName[#Headers],0),2),FALSE)) | U1389: =IF(VALUE(V1389)=0,"",V1389&"-"&W1389) | V1389: 0 | W1389: =IF(V1389<>0,VLOOKUP(VLOOKUP(V1389,Tbl_Effect[],3,FALSE),EffectName[],IFERROR(MATCH(UI!$B$1,EffectName[#Headers],0),2),FALSE),"") | X1389: =IF(VALUE(Y1389)=0,"",Y1389&"-"&Z1389) | Y1389: 0 | Z1389: =IF(Y1389<>0,VLOOKUP(VLOOKUP(Y1389,Tbl_Effect[],3,FALSE),EffectName[],IFERROR(MATCH(UI!$B$1,EffectName[#Headers],0),2),FALSE),"") | AA1389: =IF(VALUE(AB1389)=0,"",AB1389&"-"&AC1389) | AB1389: 0 | AC1389: =IF(AB1389<>0,VLOOKUP(VLOOKUP(AB1389,Tbl_Effect[],3,FALSE),EffectName[],IFERROR(MATCH(UI!$B$1,EffectName[#Headers],0),2),FALSE),"")
H1390: =IF(VALUE(I1390)<>0,I1390&"-"&K1390&" ("&J1390&")","") | I1390: 0 | J1390: =_xlfn.IFNA(IF(I1390<>0,VLOOKUP(VLOOKUP(I1390,Tbl_Equip[],2,FALSE),Tbl_Color[],IFERROR(MATCH(UI!$B$1,Tbl_Color[#Headers],0),2),FALSE),""),"Unset") | K1390: =_xlfn.IFNA(IF(I1390<>0,VLOOKUP(I1390,ItemText[],IFERROR(MATCH(UI!$B$1,ItemText[#Headers],0),2),FALSE),""),"Unset") | M1390: 0 | P1390: 0 | S1390: 0 | T1390: =IF(VALUE(S1390)=0,"",VLOOKUP(VLOOKUP(S1390,Tbl_Effect[],3,FALSE),EffectName[],IFERROR(MATCH(UI!$B$1,EffectName[#Headers],0),2),FALSE)) | U1390: =IF(VALUE(V1390)=0,"",V1390&"-"&W1390) | V1390: 0 | W1390: =IF(V1390<>0,VLOOKUP(VLOOKUP(V1390,Tbl_Effect[],3,FALSE),EffectName[],IFERROR(MATCH(UI!$B$1,EffectName[#Headers],0),2),FALSE),"") | X1390: =IF(VALUE(Y1390)=0,"",Y1390&"-"&Z1390) | Y1390: 0 | Z1390: =IF(Y1390<>0,VLOOKUP(VLOOKUP(Y1390,Tbl_Effect[],3,FALSE),EffectName[],IFERROR(MATCH(UI!$B$1,EffectName[#Headers],0),2),FALSE),"") | AA1390: =IF(VALUE(AB1390)=0,"",AB1390&"-"&AC1390) | AB1390: 0 | AC1390: =IF(AB1390<>0,VLOOKUP(VLOOKUP(AB1390,Tbl_Effect[],3,FALSE),EffectName[],IFERROR(MATCH(UI!$B$1,EffectName[#Headers],0),2),FALSE),"")
H1391: =IF(VALUE(I1391)<>0,I1391&"-"&K1391&" ("&J1391&")","") | I1391: 0 | J1391: =_xlfn.IFNA(IF(I1391<>0,VLOOKUP(VLOOKUP(I1391,Tbl_Equip[],2,FALSE),Tbl_Color[],IFERROR(MATCH(UI!$B$1,Tbl_Color[#Headers],0),2),FALSE),""),"Unset") | K1391: =_xlfn.IFNA(IF(I1391<>0,VLOOKUP(I1391,ItemText[],IFERROR(MATCH(UI!$B$1,ItemText[#Headers],0),2),FALSE),""),"Unset") | M1391: 0 | P1391: 0 | S1391: 0 | T1391: =IF(VALUE(S1391)=0,"",VLOOKUP(VLOOKUP(S1391,Tbl_Effect[],3,FALSE),EffectName[],IFERROR(MATCH(UI!$B$1,EffectName[#Headers],0),2),FALSE)) | U1391: =IF(VALUE(V1391)=0,"",V1391&"-"&W1391) | V1391: 0 | W1391: =IF(V1391<>0,VLOOKUP(VLOOKUP(V1391,Tbl_Effect[],3,FALSE),EffectName[],IFERROR(MATCH(UI!$B$1,EffectName[#Headers],0),2),FALSE),"") | X1391: =IF(VALUE(Y1391)=0,"",Y1391&"-"&Z1391) | Y1391: 0 | Z1391: =IF(Y1391<>0,VLOOKUP(VLOOKUP(Y1391,Tbl_Effect[],3,FALSE),EffectName[],IFERROR(MATCH(UI!$B$1,EffectName[#Headers],0),2),FALSE),"") | AA1391: =IF(VALUE(AB1391)=0,"",AB1391&"-"&AC1391) | AB1391: 0 | AC1391: =IF(AB1391<>0,VLOOKUP(VLOOKUP(AB1391,Tbl_Effect[],3,FALSE),EffectName[],IFERROR(MATCH(UI!$B$1,EffectName[#Headers],0),2),FALSE),"")
H1392: =IF(VALUE(I1392)<>0,I1392&"-"&K1392&" ("&J1392&")","") | I1392: 0 | J1392: =_xlfn.IFNA(IF(I1392<>0,VLOOKUP(VLOOKUP(I1392,Tbl_Equip[],2,FALSE),Tbl_Color[],IFERROR(MATCH(UI!$B$1,Tbl_Color[#Headers],0),2),FALSE),""),"Unset") | K1392: =_xlfn.IFNA(IF(I1392<>0,VLOOKUP(I1392,ItemText[],IFERROR(MATCH(UI!$B$1,ItemText[#Headers],0),2),FALSE),""),"Unset") | M1392: 0 | P1392: 0 | S1392: 0 | T1392: =IF(VALUE(S1392)=0,"",VLOOKUP(VLOOKUP(S1392,Tbl_Effect[],3,FALSE),EffectName[],IFERROR(MATCH(UI!$B$1,EffectName[#Headers],0),2),FALSE)) | U1392: =IF(VALUE(V1392)=0,"",V1392&"-"&W1392) | V1392: 0 | W1392: =IF(V1392<>0,VLOOKUP(VLOOKUP(V1392,Tbl_Effect[],3,FALSE),EffectName[],IFERROR(MATCH(UI!$B$1,EffectName[#Headers],0),2),FALSE),"") | X1392: =IF(VALUE(Y1392)=0,"",Y1392&"-"&Z1392) | Y1392: 0 | Z1392: =IF(Y1392<>0,VLOOKUP(VLOOKUP(Y1392,Tbl_Effect[],3,FALSE),EffectName[],IFERROR(MATCH(UI!$B$1,EffectName[#Headers],0),2),FALSE),"") | AA1392: =IF(VALUE(AB1392)=0,"",AB1392&"-"&AC1392) | AB1392: 0 | AC1392: =IF(AB1392<>0,VLOOKUP(VLOOKUP(AB1392,Tbl_Effect[],3,FALSE),EffectName[],IFERROR(MATCH(UI!$B$1,EffectName[#Headers],0),2),FALSE),"")
H1393: =IF(VALUE(I1393)<>0,I1393&"-"&K1393&" ("&J1393&")","") | I1393: 0 | J1393: =_xlfn.IFNA(IF(I1393<>0,VLOOKUP(VLOOKUP(I1393,Tbl_Equip[],2,FALSE),Tbl_Color[],IFERROR(MATCH(UI!$B$1,Tbl_Color[#Headers],0),2),FALSE),""),"Unset") | K1393: =_xlfn.IFNA(IF(I1393<>0,VLOOKUP(I1393,ItemText[],IFERROR(MATCH(UI!$B$1,ItemText[#Headers],0),2),FALSE),""),"Unset") | M1393: 0 | P1393: 0 | S1393: 0 | T1393: =IF(VALUE(S1393)=0,"",VLOOKUP(VLOOKUP(S1393,Tbl_Effect[],3,FALSE),EffectName[],IFERROR(MATCH(UI!$B$1,EffectName[#Headers],0),2),FALSE)) | U1393: =IF(VALUE(V1393)=0,"",V1393&"-"&W1393) | V1393: 0 | W1393: =IF(V1393<>0,VLOOKUP(VLOOKUP(V1393,Tbl_Effect[],3,FALSE),EffectName[],IFERROR(MATCH(UI!$B$1,EffectName[#Headers],0),2),FALSE),"") | X1393: =IF(VALUE(Y1393)=0,"",Y1393&"-"&Z1393) | Y1393: 0 | Z1393: =IF(Y1393<>0,VLOOKUP(VLOOKUP(Y1393,Tbl_Effect[],3,FALSE),EffectName[],IFERROR(MATCH(UI!$B$1,EffectName[#Headers],0),2),FALSE),"") | AA1393: =IF(VALUE(AB1393)=0,"",AB1393&"-"&AC1393) | AB1393: 0 | AC1393: =IF(AB1393<>0,VLOOKUP(VLOOKUP(AB1393,Tbl_Effect[],3,FALSE),EffectName[],IFERROR(MATCH(UI!$B$1,EffectName[#Headers],0),2),FALSE),"")
H1394: =IF(VALUE(I1394)<>0,I1394&"-"&K1394&" ("&J1394&")","") | I1394: 0 | J1394: =_xlfn.IFNA(IF(I1394<>0,VLOOKUP(VLOOKUP(I1394,Tbl_Equip[],2,FALSE),Tbl_Color[],IFERROR(MATCH(UI!$B$1,Tbl_Color[#Headers],0),2),FALSE),""),"Unset") | K1394: =_xlfn.IFNA(IF(I1394<>0,VLOOKUP(I1394,ItemText[],IFERROR(MATCH(UI!$B$1,ItemText[#Headers],0),2),FALSE),""),"Unset") | M1394: 0 | P1394: 0 | S1394: 0 | T1394: =IF(VALUE(S1394)=0,"",VLOOKUP(VLOOKUP(S1394,Tbl_Effect[],3,FALSE),EffectName[],IFERROR(MATCH(UI!$B$1,EffectName[#Headers],0),2),FALSE)) | U1394: =IF(VALUE(V1394)=0,"",V1394&"-"&W1394) | V1394: 0 | W1394: =IF(V1394<>0,VLOOKUP(VLOOKUP(V1394,Tbl_Effect[],3,FALSE),EffectName[],IFERROR(MATCH(UI!$B$1,EffectName[#Headers],0),2),FALSE),"") | X1394: =IF(VALUE(Y1394)=0,"",Y1394&"-"&Z1394) | Y1394: 0 | Z1394: =IF(Y1394<>0,VLOOKUP(VLOOKUP(Y1394,Tbl_Effect[],3,FALSE),EffectName[],IFERROR(MATCH(UI!$B$1,EffectName[#Headers],0),2),FALSE),"") | AA1394: =IF(VALUE(AB1394)=0,"",AB1394&"-"&AC1394) | AB1394: 0 | AC1394: =IF(AB1394<>0,VLOOKUP(VLOOKUP(AB1394,Tbl_Effect[],3,FALSE),EffectName[],IFERROR(MATCH(UI!$B$1,EffectName[#Headers],0),2),FALSE),"")
H1395: =IF(VALUE(I1395)<>0,I1395&"-"&K1395&" ("&J1395&")","") | I1395: 0 | J1395: =_xlfn.IFNA(IF(I1395<>0,VLOOKUP(VLOOKUP(I1395,Tbl_Equip[],2,FALSE),Tbl_Color[],IFERROR(MATCH(UI!$B$1,Tbl_Color[#Headers],0),2),FALSE),""),"Unset") | K1395: =_xlfn.IFNA(IF(I1395<>0,VLOOKUP(I1395,ItemText[],IFERROR(MATCH(UI!$B$1,ItemText[#Headers],0),2),FALSE),""),"Unset") | M1395: 0 | P1395: 0 | S1395: 0 | T1395: =IF(VALUE(S1395)=0,"",VLOOKUP(VLOOKUP(S1395,Tbl_Effect[],3,FALSE),EffectName[],IFERROR(MATCH(UI!$B$1,EffectName[#Headers],0),2),FALSE)) | U1395: =IF(VALUE(V1395)=0,"",V1395&"-"&W1395) | V1395: 0 | W1395: =IF(V1395<>0,VLOOKUP(VLOOKUP(V1395,Tbl_Effect[],3,FALSE),EffectName[],IFERROR(MATCH(UI!$B$1,EffectName[#Headers],0),2),FALSE),"") | X1395: =IF(VALUE(Y1395)=0,"",Y1395&"-"&Z1395) | Y1395: 0 | Z1395: =IF(Y1395<>0,VLOOKUP(VLOOKUP(Y1395,Tbl_Effect[],3,FALSE),EffectName[],IFERROR(MATCH(UI!$B$1,EffectName[#Headers],0),2),FALSE),"") | AA1395: =IF(VALUE(AB1395)=0,"",AB1395&"-"&AC1395) | AB1395: 0 | AC1395: =IF(AB1395<>0,VLOOKUP(VLOOKUP(AB1395,Tbl_Effect[],3,FALSE),EffectName[],IFERROR(MATCH(UI!$B$1,EffectName[#Headers],0),2),FALSE),"")
H1396: =IF(VALUE(I1396)<>0,I1396&"-"&K1396&" ("&J1396&")","") | I1396: 0 | J1396: =_xlfn.IFNA(IF(I1396<>0,VLOOKUP(VLOOKUP(I1396,Tbl_Equip[],2,FALSE),Tbl_Color[],IFERROR(MATCH(UI!$B$1,Tbl_Color[#Headers],0),2),FALSE),""),"Unset") | K1396: =_xlfn.IFNA(IF(I1396<>0,VLOOKUP(I1396,ItemText[],IFERROR(MATCH(UI!$B$1,ItemText[#Headers],0),2),FALSE),""),"Unset") | M1396: 0 | P1396: 0 | S1396: 0 | T1396: =IF(VALUE(S1396)=0,"",VLOOKUP(VLOOKUP(S1396,Tbl_Effect[],3,FALSE),EffectName[],IFERROR(MATCH(UI!$B$1,EffectName[#Headers],0),2),FALSE)) | U1396: =IF(VALUE(V1396)=0,"",V1396&"-"&W1396) | V1396: 0 | W1396: =IF(V1396<>0,VLOOKUP(VLOOKUP(V1396,Tbl_Effect[],3,FALSE),EffectName[],IFERROR(MATCH(UI!$B$1,EffectName[#Headers],0),2),FALSE),"") | X1396: =IF(VALUE(Y1396)=0,"",Y1396&"-"&Z1396) | Y1396: 0 | Z1396: =IF(Y1396<>0,VLOOKUP(VLOOKUP(Y1396,Tbl_Effect[],3,FALSE),EffectName[],IFERROR(MATCH(UI!$B$1,EffectName[#Headers],0),2),FALSE),"") | AA1396: =IF(VALUE(AB1396)=0,"",AB1396&"-"&AC1396) | AB1396: 0 | AC1396: =IF(AB1396<>0,VLOOKUP(VLOOKUP(AB1396,Tbl_Effect[],3,FALSE),EffectName[],IFERROR(MATCH(UI!$B$1,EffectName[#Headers],0),2),FALSE),"")
H1397: =IF(VALUE(I1397)<>0,I1397&"-"&K1397&" ("&J1397&")","") | I1397: 0 | J1397: =_xlfn.IFNA(IF(I1397<>0,VLOOKUP(VLOOKUP(I1397,Tbl_Equip[],2,FALSE),Tbl_Color[],IFERROR(MATCH(UI!$B$1,Tbl_Color[#Headers],0),2),FALSE),""),"Unset") | K1397: =_xlfn.IFNA(IF(I1397<>0,VLOOKUP(I1397,ItemText[],IFERROR(MATCH(UI!$B$1,ItemText[#Headers],0),2),FALSE),""),"Unset") | M1397: 0 | P1397: 0 | S1397: 0 | T1397: =IF(VALUE(S1397)=0,"",VLOOKUP(VLOOKUP(S1397,Tbl_Effect[],3,FALSE),EffectName[],IFERROR(MATCH(UI!$B$1,EffectName[#Headers],0),2),FALSE)) | U1397: =IF(VALUE(V1397)=0,"",V1397&"-"&W1397) | V1397: 0 | W1397: =IF(V1397<>0,VLOOKUP(VLOOKUP(V1397,Tbl_Effect[],3,FALSE),EffectName[],IFERROR(MATCH(UI!$B$1,EffectName[#Headers],0),2),FALSE),"") | X1397: =IF(VALUE(Y1397)=0,"",Y1397&"-"&Z1397) | Y1397: 0 | Z1397: =IF(Y1397<>0,VLOOKUP(VLOOKUP(Y1397,Tbl_Effect[],3,FALSE),EffectName[],IFERROR(MATCH(UI!$B$1,EffectName[#Headers],0),2),FALSE),"") | AA1397: =IF(VALUE(AB1397)=0,"",AB1397&"-"&AC1397) | AB1397: 0 | AC1397: =IF(AB1397<>0,VLOOKUP(VLOOKUP(AB1397,Tbl_Effect[],3,FALSE),EffectName[],IFERROR(MATCH(UI!$B$1,EffectName[#Headers],0),2),FALSE),"")
H1398: =IF(VALUE(I1398)<>0,I1398&"-"&K1398&" ("&J1398&")","") | I1398: 0 | J1398: =_xlfn.IFNA(IF(I1398<>0,VLOOKUP(VLOOKUP(I1398,Tbl_Equip[],2,FALSE),Tbl_Color[],IFERROR(MATCH(UI!$B$1,Tbl_Color[#Headers],0),2),FALSE),""),"Unset") | K1398: =_xlfn.IFNA(IF(I1398<>0,VLOOKUP(I1398,ItemText[],IFERROR(MATCH(UI!$B$1,ItemText[#Headers],0),2),FALSE),""),"Unset") | M1398: 0 | P1398: 0 | S1398: 0 | T1398: =IF(VALUE(S1398)=0,"",VLOOKUP(VLOOKUP(S1398,Tbl_Effect[],3,FALSE),EffectName[],IFERROR(MATCH(UI!$B$1,EffectName[#Headers],0),2),FALSE)) | U1398: =IF(VALUE(V1398)=0,"",V1398&"-"&W1398) | V1398: 0 | W1398: =IF(V1398<>0,VLOOKUP(VLOOKUP(V1398,Tbl_Effect[],3,FALSE),EffectName[],IFERROR(MATCH(UI!$B$1,EffectName[#Headers],0),2),FALSE),"") | X1398: =IF(VALUE(Y1398)=0,"",Y1398&"-"&Z1398) | Y1398: 0 | Z1398: =IF(Y1398<>0,VLOOKUP(VLOOKUP(Y1398,Tbl_Effect[],3,FALSE),EffectName[],IFERROR(MATCH(UI!$B$1,EffectName[#Headers],0),2),FALSE),"") | AA1398: =IF(VALUE(AB1398)=0,"",AB1398&"-"&AC1398) | AB1398: 0 | AC1398: =IF(AB1398<>0,VLOOKUP(VLOOKUP(AB1398,Tbl_Effect[],3,FALSE),EffectName[],IFERROR(MATCH(UI!$B$1,EffectName[#Headers],0),2),FALSE),"")
... H2000: =IF(VALUE(I2000)<>0,I2000&"-"&K2000&" ("&J2000&")","") | I2000: 0 | J2000: =_xlfn.IFNA(IF(I2000<>0,VLOOKUP(VLOOKUP(I2000,Tbl_Equip[],2,FALSE),Tbl_Color[],IFERROR(MATCH(UI!$B$1,Tbl_Color[#Headers],0),2),FALSE),""),"Unset") | K2000: =_xlfn.IFNA(IF(I2000<>0,VLOOKUP(I2000,ItemText[],IFERROR(MATCH(UI!$B$1,ItemText[#Headers],0),2),FALSE),""),"Unset") | M2000: 0 | P2000: 0 | S2000: 0 | T2000: =IF(VALUE(S2000)=0,"",VLOOKUP(VLOOKUP(S2000,Tbl_Effect[],3,FALSE),EffectName[],IFERROR(MATCH(UI!$B$1,EffectName[#Headers],0),2),FALSE)) | U2000: =IF(VALUE(V2000)=0,"",V2000&"-"&W2000) | V2000: 0 | W2000: =IF(V2000<>0,VLOOKUP(VLOOKUP(V2000,Tbl_Effect[],3,FALSE),EffectName[],IFERROR(MATCH(UI!$B$1,EffectName[#Headers],0),2),FALSE),"") | X2000: =IF(VALUE(Y2000)=0,"",Y2000&"-"&Z2000) | Y2000: 0 | Z2000: =IF(Y2000<>0,VLOOKUP(VLOOKUP(Y2000,Tbl_Effect[],3,FALSE),EffectName[],IFERROR(MATCH(UI!$B$1,EffectName[#Headers],0),2),FALSE),"") | AA2000: =IF(VALUE(AB2000)=0,"",AB2000&"-"&AC2000) | AB2000: 0 | AC2000: =IF(AB2000<>0,VLOOKUP(VLOOKUP(AB2000,Tbl_Effect[],3,FALSE),EffectName[],IFERROR(MATCH(UI!$B$1,EffectName[#Headers],0),2),FALSE),"")
I2001: 0 | J2001: =_xlfn.IFNA(IF(I2001<>0,VLOOKUP(VLOOKUP(I2001,Tbl_Equip[],2,FALSE),Tbl_Color[],IFERROR(MATCH(UI!$B$1,Tbl_Color[#Headers],0),2),FALSE),""),"Unset") | K2001: =_xlfn.IFNA(IF(I2001<>0,VLOOKUP(I2001,ItemText[],IFERROR(MATCH(UI!$B$1,ItemText[#Headers],0),2),FALSE),""),"Unset") | M2001: 0 | P2001: 0 | S2001: 0 | T2001: =IF(VALUE(S2001)=0,"",VLOOKUP(VLOOKUP(S2001,Tbl_Effect[],3,FALSE),EffectName[],IFERROR(MATCH(UI!$B$1,EffectName[#Headers],0),2),FALSE)) | U2001: =IF(VALUE(V2001)=0,"",V2001&"-"&W2001) | V2001: 0 | W2001: =IF(V2001<>0,VLOOKUP(VLOOKUP(V2001,Tbl_Effect[],3,FALSE),EffectName[],IFERROR(MATCH(UI!$B$1,EffectName[#Headers],0),2),FALSE),"") | X2001: =IF(VALUE(Y2001)=0,"",Y2001&"-"&Z2001) | Y2001: 0 | Z2001: =IF(Y2001<>0,VLOOKUP(VLOOKUP(Y2001,Tbl_Effect[],3,FALSE),EffectName[],IFERROR(MATCH(UI!$B$1,EffectName[#Headers],0),2),FALSE),"") | AA2001: =IF(VALUE(AB2001)=0,"",AB2001&"-"&AC2001) | AB2001: 0 | AC2001: =IF(AB2001<>0,VLOOKUP(VLOOKUP(AB2001,Tbl_Effect[],3,FALSE),EffectName[],IFERROR(MATCH(UI!$B$1,EffectName[#Headers],0),2),FALSE),"")

Sheet Tbl_Equip
A1: ID | B1: relicColor | C1: attachEffectTableId_1 | D1: attachEffectTableId_2 | E1: attachEffectTableId_3 | F1: iconId | G1: attachEffectTableId_curse1 | H1: attachEffectTableId_curse2 | I1: attachEffectTableId_curse3
A2: 1 | B2: 0 | C2: 501100000 | D2: -1 | E2: -1 | F2: 416 | G2: -1 | H2: -1 | I2: -1
A3: 2 | B3: 0 | C3: 501100000 | D3: 501200000 | E3: -1 | F3: 416 | G3: -1 | H3: -1 | I3: -1
A4: 3 | B4: 0 | C4: 501100000 | D4: 501200000 | E4: 501300000 | F4: 416 | G4: -1 | H4: -1 | I4: -1
A5: 4 | B5: 0 | C5: 410000001 | D5: -1 | E5: -1 | F5: 416 | G5: -1 | H5: -1 | I5: -1
A6: 5 | B6: 0 | C6: 410000002 | D6: -1 | E6: -1 | F6: 416 | G6: -1 | H6: -1 | I6: -1
A7: 6 | B7: 0 | C7: 410000003 | D7: 410000003 | E7: 410000003 | F7: 416 | G7: -1 | H7: -1 | I7: -1
A8: 10 | B8: 0 | C8: -1 | D8: -1 | E8: -1 | F8: 19951 | G8: -1 | H8: -1 | I8: -1
A9: 11 | B9: 0 | C9: -1 | D9: -1 | E9: -1 | F9: 19952 | G9: -1 | H9: -1 | I9: -1
A10: 20 | B10: 0 | C10: -1 | D10: -1 | E10: -1 | F10: 19200 | G10: -1 | H10: -1 | I10: -1
A11: 100 | B11: 0 | C11: 100 | D11: -1 | E11: -1 | F11: 19100 | G11: -1 | H11: -1 | I11: -1
A12: 101 | B12: 0 | C12: 200 | D12: 100 | E12: -1 | F12: 19104 | G12: -1 | H12: -1 | I12: -1
A13: 102 | B13: 0 | C13: 300 | D13: 200 | E13: 100 | F13: 19108 | G13: -1 | H13: -1 | I13: -1
... A1386: 7999999 | B1386: 0 | C1386: 707999999 | D1386: -1 | E1386: -1 | F1386: 428 | G1386: -1 | H1386: -1 | I1386: -1

Sheet Tbl_Pool
A1: ID | B1: attachEffectId
A2: 0 | B2: -1
A3: 100 | B3: 7000000
A4: 100 | B4: 7000001
A5: 100 | B5: 7000002
A6: 100 | B6: 7000100
A7: 100 | B7: 7000101
A8: 100 | B8: 7000102
A9: 100 | B9: 7000200
A10: 100 | B10: 7000201
A11: 100 | B11: 7000202
A12: 100 | B12: 7000300
A13: 100 | B13: 7000301
... A22089: 999999999 | B22089: -1

Sheet Tbl_Effect
A1: 欄1 | B1: compatibilityId | C1: attachTextId | D1: overrideEffectId
A2: 0 | B2: -1 | C2: -1 | D2: 0
A3: 10000 | B3: -1 | C3: 8610100 | D3: 1
A4: 10001 | B4: -1 | C4: 7032200 | D4: 1
A5: 10002 | B5: -1 | C5: 7035900 | D5: 1
A6: 11000 | B6: -1 | C6: 7033200 | D6: 1
A7: 11001 | B7: -1 | C7: 7010200 | D7: 1
A8: 11002 | B8: -1 | C8: 7032400 | D8: 1
A9: 12000 | B9: -1 | C9: 7011000 | D9: 1
A10: 12001 | B10: -1 | C10: 7030600 | D10: 1
A11: 12002 | B11: -1 | C11: 7012000 | D11: 1
A12: 12003 | B12: -1 | C12: 7012000 | D12: 1
A13: 13000 | B13: -1 | C13: 7030900 | D13: 1
... A2080: 999999999 | B2080: -1 | C2080: -1 | D2080: 0

Sheet AttachEffectName_dlc01 fmg
A1: ID | B1: 繁體中文
A2: 6500800 | B2: 【學者】對自己使用技藝時，能減少消耗的FP
A3: 6500900 | B3: 【送葬者】發動絕活後，能再次使用技藝
A4: 6623200 | B4: 出擊時，會持有「湧綠結晶露滴」
A5: 6647200 | B5: 【學者】提升集中力，但降低生命力
A6: 6647300 | B6: 【學者】提升耐力、靈巧，但降低智力、感應
A7: 6647400 | B7: 【送葬者】提升靈巧，但降低生命力、信仰
A8: 6647500 | B8: 【送葬者】提升集中力、信仰，但降低力氣
A9: 7006500 | B9: 持續恢復ＦＰ
A10: 7006600 | B10: 提升近戰攻擊力
A11: 7006700 | B11: 提升戰技攻擊力
A12: 7036200 | B12: 【學者】減緩技藝進行率的下降幅度
A13: 7036300 | B13: 【學者】使用技藝時，提升目標我方人物的攻擊力
... A55: 9991000 | B55: 送葬者的不甘

Sheet Effects
A1: ID | B1: English | C1: 繁體中文
A2: 1 | B2: %null% | C2: %null%
A3: 2 | B3: %null% | C3: %null%
A4: 3 | B4: %null% | C4: %null%
A5: 100 | B5: %null% | C5: %null%
A6: 310000 | B6: Increased Maximum HP | C6: 提升ＨＰ上限
A7: 310100 | B7: Increased Maximum FP | C7: 提升ＦＰ上限
A8: 310200 | B8: Increased Maximum Stamina | C8: 提升精力上限
A9: 310400 | B9: Increased Maximum HP | C9: 提升ＨＰ上限
A10: 310401 | B10: Increased Maximum Stamina | C10: 提升精力上限
A11: 311000 | B11: Improved Item Discovery | C11: 提升觀察力
A12: 311100 | B12: More Runes From Defeated Enemies | C12: 打倒敵人時，增加獲得的盧恩
A13: 311500 | B13: Improved Stamina Recovery | C13: 提升精力恢復速度
... A1196: 19799999 | B1196: All Options | C1196: 全選

Sheet Items
A1: ID | B1: English | C1: 繁體中文
A2: 1 | B2: Antique | C2: %null%
A3: 2 | B3: Antique | C3: %null%
A4: 3 | B4: Antique | C4: %null%
A5: 4 | B5: Antique | C5: %null%
A6: 5 | B6: Antique | C6: %null%
A7: 6 | B7: Antique | C7: %null%
A8: 7 | B8: %null% | C8: %null%
A9: 8 | B9: %null% | C9: %null%
A10: 9 | B10: %null% | C10: %null%
A11: 10 | B11: Murk | C11: 暗痕
A12: 11 | B12: Sovereign Sigil | C12: 為王之證
A13: 12 | B13: %null% | C13: %null%
... A2637: 2013322 | B2637: Deep Grand Tranquil Scene | C2637: 遼闊的幽靜暗淡情景

Sheet Variable
A1: 欄1 | C1: ID | D1: English | E1: 繁體中文 | F1: 简体中文 | H1: EmptyID
A2: {=LEFT(CELL("filename",A2), FIND("[",CELL("filename",A2))-1)} -> C:\Users\ShockDaWae\AppData\Roaming\Microsoft\Excel\ | C2: 0 | D2: Red | E2: 紅 | F2: 红 | H2: 4294967295
C3: 1 | D3: Blue | E3: 藍 | F3: 蓝
C4: 2 | D4: Yellow | E4: 黃 | F4: 黄
C5: 3 | D5: Green | E5: 綠 | F5: 绿
